[{"8r8Vp_1iB4k": {"Slope of a line secant to a curve | Taking derivatives | Differential Calculus | Khan Academy": {"channel_id": "UgwSAf12WIuVriadAUp4AaABAg", "comment_by": "I Putu Artha Wirawan", "comment_text": "Thank you", "comment_date": "2022-02-18T09:09:42Z", "likes_count": 0}}}, {"8r8Vp_1iB4k": {"Slope of a line secant to a curve | Taking derivatives | Differential Calculus | Khan Academy": {"channel_id": "UgwiJgVIkG3n0cdy0HR4AaABAg", "comment_by": "lovely littlegirl", "comment_text": "(x not, why not?)", "comment_date": "2020-09-17T17:47:31Z", "likes_count": 1}}}, {"8r8Vp_1iB4k": {"Slope of a line secant to a curve | Taking derivatives | Differential Calculus | Khan Academy": {"channel_id": "UgxkTJ5WmvijPswyv6Z4AaABAg", "comment_by": "Veer Chopra", "comment_text": "Sal all the way!", "comment_date": "2020-03-19T23:26:28Z", "likes_count": 2}}}, {"8r8Vp_1iB4k": {"Slope of a line secant to a curve | Taking derivatives | Differential Calculus | Khan Academy": {"channel_id": "UgzIJt-FWA4SQq7HgnN4AaABAg", "comment_by": "Joshua Kaumba", "comment_text": "X  subzero Haha get it like mortal kombat.", "comment_date": "2020-03-16T16:56:17Z", "likes_count": 0}}}, {"8r8Vp_1iB4k": {"Slope of a line secant to a curve | Taking derivatives | Differential Calculus | Khan Academy": {"channel_id": "Ugz2RCPfa2scj38IqeR4AaABAg", "comment_by": "zahraa rammal", "comment_text": "I did not get anything, can you write an example questions...", "comment_date": "2019-01-07T12:53:34Z", "likes_count": 2}}}, {"8r8Vp_1iB4k": {"Slope of a line secant to a curve | Taking derivatives | Differential Calculus | Khan Academy": {"channel_id": "UgyWk0BashRP_2efcU14AaABAg", "comment_by": "Melissa Saucedo", "comment_text": "not that helpful. i watched this video for help with calculus, not a review of algebra", "comment_date": "2018-09-16T15:21:21Z", "likes_count": 16}}}, {"8r8Vp_1iB4k": {"Slope of a line secant to a curve | Taking derivatives | Differential Calculus | Khan Academy": {"channel_id": "UggJg4O_pRVrX3gCoAEC", "comment_by": "Dophie15", "comment_text": "Sal has taught me more than my Biology, accounting, economics, algebra and calculus professors combined! you the real MVP", "comment_date": "2017-06-13T15:01:19Z", "likes_count": 20}}}, {"8r8Vp_1iB4k": {"Slope of a line secant to a curve | Taking derivatives | Differential Calculus | Khan Academy": {"channel_id": "Ugh6uaLyq6VKAXgCoAEC", "comment_by": "Chief Judge", "comment_text": "Republicans are stupid.", "comment_date": "2016-06-13T05:07:15Z", "likes_count": 7}}}, {"8r8Vp_1iB4k": {"Slope of a line secant to a curve | Taking derivatives | Differential Calculus | Khan Academy": {"channel_id": "UgjxU8gddGTpRngCoAEC", "comment_by": "Umesh G J", "comment_text": "Mind blowing...explaination", "comment_date": "2016-04-25T14:50:02Z", "likes_count": 9}}}, {"8r8Vp_1iB4k": {"Slope of a line secant to a curve | Taking derivatives | Differential Calculus | Khan Academy": {"channel_id": "Ugj51nsFk0eH5ngCoAEC", "comment_by": "CalebTheObjective", "comment_text": "Sure lets find the line...Y naut?", "comment_date": "2016-03-15T05:51:45Z", "likes_count": 36}}}, {"8r8Vp_1iB4k": {"Slope of a line secant to a curve | Taking derivatives | Differential Calculus | Khan Academy": {"channel_id": "Ugg9Tjds0SNySXgCoAEC", "comment_by": "DOGE[tm] responds to old comments", "comment_text": "Third comment woo!", "comment_date": "2015-11-08T22:12:14Z", "likes_count": 1}}}, {"8r8Vp_1iB4k": {"Slope of a line secant to a curve | Taking derivatives | Differential Calculus | Khan Academy": {"channel_id": "UggFDQS-jFeeungCoAEC", "comment_by": "Gost", "comment_text": "khan academy for everything,", "comment_date": "2014-04-25T04:36:40Z", "likes_count": 12}}}]