[{"comment_by": "Shadow Soulless", "comment_text": "<a href=\"https://www.youtube.com/watch?v=n7xg7OZHqKs&amp;t=2m49s\">2:49</a> that was the part you came to see", "comment_date": "2022-03-28T23:22:11Z", "likes_count": 0}, {"comment_by": "Jaana Rodrigo", "comment_text": "he was literally my childhood. i burst into tears when i found out he had passed because i didn\u2019t even know it had happened.", "comment_date": "2021-03-04T06:57:53Z", "likes_count": 1}, {"comment_by": "Cristian llanes", "comment_text": "Did they even talk about his death or no", "comment_date": "2021-03-01T05:32:05Z", "likes_count": 0}, {"comment_by": "D\u00e9sch Music", "comment_text": "Anyone wondering why he did not upload anything else for  about 4 months until he passed away ? RIP \u2665\ufe0f", "comment_date": "2020-12-29T22:52:32Z", "likes_count": 0}, {"comment_by": "Raimond223", "comment_text": "Rest in peace. I loved your content", "comment_date": "2020-10-31T22:28:02Z", "likes_count": 0}, {"comment_by": "henwardo henningson", "comment_text": "I miss watching his videos \ud83d\ude14", "comment_date": "2020-09-21T04:22:15Z", "likes_count": 0}, {"comment_by": "Spencrr", "comment_text": "rip", "comment_date": "2020-08-17T06:42:18Z", "likes_count": 0}, {"comment_by": "Ben Plays", "comment_text": "The last video he was in", "comment_date": "2020-07-30T20:12:20Z", "likes_count": 0}, {"comment_by": "Yatto_o0", "comment_text": "This dude he dead", "comment_date": "2020-06-25T23:25:28Z", "likes_count": 0}, {"comment_by": "ANONYMOUS", "comment_text": "RIP GRANT THOMPSON/KING OF RANDOM", "comment_date": "2020-06-13T14:30:58Z", "likes_count": 0}, {"comment_by": "Randomized Productions", "comment_text": "Who else came here to see his last video he was in", "comment_date": "2020-06-07T01:41:54Z", "likes_count": 0}, {"comment_by": "Kevin", "comment_text": "I loved this guy, felt heartbroken when i heard about him passing away, even i hadn\u2019t realized how much i loved him", "comment_date": "2020-05-10T00:05:06Z", "likes_count": 1}, {"comment_by": "falsedeath", "comment_text": "I teared up when he said &quot;see you in the next video&quot; :(", "comment_date": "2020-05-09T17:42:31Z", "likes_count": 0}, {"comment_by": "UNITY", "comment_text": "hey i miss u", "comment_date": "2020-05-04T07:51:09Z", "likes_count": 0}, {"comment_by": "how is it fliping", "comment_text": "RIP", "comment_date": "2020-04-29T15:37:05Z", "likes_count": 0}, {"comment_by": "Supa Gai", "comment_text": "Rip", "comment_date": "2020-02-08T10:30:43Z", "likes_count": 0}, {"comment_by": "Fausto Ramon", "comment_text": "RIP thank you for everything :_)", "comment_date": "2020-01-15T05:42:58Z", "likes_count": 0}, {"comment_by": "Caleb Moore", "comment_text": "Missing this guy.", "comment_date": "2020-01-08T05:07:48Z", "likes_count": 0}, {"comment_by": "Donald Currie", "comment_text": "Rip", "comment_date": "2020-01-02T04:46:10Z", "likes_count": 0}, {"comment_by": "ZapTrap", "comment_text": "He deserves to be in youtuber rewind why everyone forgot about him", "comment_date": "2019-12-29T18:19:49Z", "likes_count": 2}, {"comment_by": "t0pREMAG", "comment_text": "&quot;See ya next video&quot; \ud83d\ude2d", "comment_date": "2019-12-26T09:34:25Z", "likes_count": 8}, {"comment_by": "Dometric", "comment_text": "I&#39;ve been watching him for years and now he is gone.. \ud83d\ude22\ud83d\ude22\ud83d\ude22\ud83d\ude22<br>RIP", "comment_date": "2019-12-15T10:13:54Z", "likes_count": 1}, {"comment_by": "Devin Romero", "comment_text": "Were is he", "comment_date": "2019-12-02T06:45:14Z", "likes_count": 1}, {"comment_by": "Fernando pasini", "comment_text": "It will be sorely missed for all of us", "comment_date": "2019-11-20T21:55:07Z", "likes_count": 0}, {"comment_by": "triggered pancake", "comment_text": "How?????? He was a amazing, healthy person! Why was he just ripped away?", "comment_date": "2019-11-16T02:35:44Z", "likes_count": 2}, {"comment_by": "Avin C.G.F", "comment_text": "Is this his last vid", "comment_date": "2019-11-07T00:41:37Z", "likes_count": 1}, {"comment_by": "TV FLIGHT", "comment_text": "He said see you in the next video \ud83d\ude2d\ud83d\ude2d\ud83d\ude2d", "comment_date": "2019-08-11T09:25:45Z", "likes_count": 3}, {"comment_by": "Watt Matt\u2019s dad", "comment_text": "Last video \u2764\ufe0f\u2764\ufe0f rip dude", "comment_date": "2019-08-09T22:00:18Z", "likes_count": 3}, {"comment_by": "Williams Yang", "comment_text": "\ud83d\ude22 \ud83d\ude22 \ud83d\ude22", "comment_date": "2019-08-08T20:09:23Z", "likes_count": 1}, {"comment_by": "Carmela L", "comment_text": "His last video \ud83d\ude1e\ud83d\ude22\ud83e\udd7a", "comment_date": "2019-08-06T01:52:36Z", "likes_count": 1}, {"comment_by": "Solar Pex", "comment_text": "We should all binge watch all 700 videos", "comment_date": "2019-08-04T01:37:37Z", "likes_count": 2}, {"comment_by": "Ducky D", "comment_text": "Rest easy bro \u2764\ufe0f\u2764\ufe0f\u2764\ufe0f\u2764\ufe0f\u2764\ufe0f\u2764\ufe0f\u2764\ufe0f\ud83d\ude2d\ud83d\ude2d\ud83d\ude2d", "comment_date": "2019-08-04T00:53:04Z", "likes_count": 0}, {"comment_by": "genface", "comment_text": "Rest in peace my guy sad seeing you pass after all these years my condolences go to his family and friends\ud83d\ude2a", "comment_date": "2019-08-03T18:11:03Z", "likes_count": 1}, {"comment_by": "_TEEJAY TV DUBAI_", "comment_text": "Rest in peace your the legend we love u so much", "comment_date": "2019-08-03T09:12:58Z", "likes_count": 1}, {"comment_by": "R Nation", "comment_text": "My favorite video is the pocket shots", "comment_date": "2019-08-02T11:04:37Z", "likes_count": 0}, {"comment_by": "Toge Inumaki", "comment_text": "Who knew that this would be his last rewind video?", "comment_date": "2019-08-02T10:08:39Z", "likes_count": 0}, {"comment_by": "ahmed mohamed", "comment_text": "RIP", "comment_date": "2019-08-02T08:01:42Z", "likes_count": 0}, {"comment_by": "Isabel Weaver", "comment_text": "Rip love your vids hope your making your own wings and fly high in the sky", "comment_date": "2019-08-02T07:33:33Z", "likes_count": 1}, {"comment_by": "Panthxrr", "comment_text": "Unbelievable, rest in peace :(", "comment_date": "2019-08-01T21:25:22Z", "likes_count": 2}, {"comment_by": "Bully Maguire", "comment_text": "I will miss you &lt;/3", "comment_date": "2019-08-01T20:49:39Z", "likes_count": 0}, {"comment_by": "LifeWithBob", "comment_text": "rip", "comment_date": "2019-08-01T19:35:06Z", "likes_count": 0}, {"comment_by": "Its_wavez", "comment_text": "Rip", "comment_date": "2019-08-01T18:58:55Z", "likes_count": 0}, {"comment_by": "YOUP", "comment_text": "R.I.P grand", "comment_date": "2019-08-01T16:41:38Z", "likes_count": 0}, {"comment_by": "Nathan", "comment_text": "Rest in peace man", "comment_date": "2019-08-01T14:29:07Z", "likes_count": 0}, {"comment_by": "GrixxlyBexr", "comment_text": "F", "comment_date": "2019-08-01T10:13:28Z", "likes_count": 0}, {"comment_by": "Angel France", "comment_text": "I learned so many things from him. I will miss him so much \ud83d\ude22", "comment_date": "2019-08-01T09:36:27Z", "likes_count": 2}, {"comment_by": "DV DEVO", "comment_text": "R.I.P KING\ud83d\ude13", "comment_date": "2019-08-01T09:04:47Z", "likes_count": 1}, {"comment_by": "Liam Gwinnis", "comment_text": "Rip king.", "comment_date": "2019-08-01T08:54:10Z", "likes_count": 1}, {"comment_by": "MisterLiker", "comment_text": "RIP", "comment_date": "2019-08-01T06:42:04Z", "likes_count": 0}, {"comment_by": "Daniel Montiel", "comment_text": "Dang and he passed away\ud83d\ude1e\ud83d\ude1e\ud83d\ude1e", "comment_date": "2019-08-01T06:02:47Z", "likes_count": 1}, {"comment_by": "Brayden Gallagher", "comment_text": "RIP to a goat", "comment_date": "2019-08-01T05:39:08Z", "likes_count": 0}, {"comment_by": "kaif khan", "comment_text": "Imagine dying\ud83d\udc80", "comment_date": "2019-08-01T03:19:41Z", "likes_count": 0}, {"comment_by": "Grant Fredrickson", "comment_text": "<b>RIP</b>", "comment_date": "2019-08-01T01:18:50Z", "likes_count": 0}, {"comment_by": "Neal Cordova", "comment_text": "RIP \ud83d\ude22", "comment_date": "2019-08-01T00:35:40Z", "likes_count": 0}, {"comment_by": "SoMeThInGgReAt", "comment_text": "RIP\ud83d\ude2d", "comment_date": "2019-07-31T20:53:06Z", "likes_count": 0}, {"comment_by": "Armando Beck", "comment_text": "R.I.P King of Random", "comment_date": "2019-07-31T20:29:49Z", "likes_count": 0}, {"comment_by": "Deleon", "comment_text": "Last Real KOR Vid, We will always have you in our hearts.", "comment_date": "2019-07-31T18:23:12Z", "likes_count": 7}, {"comment_by": "Roko Svalina", "comment_text": "R. I. P true King of random", "comment_date": "2019-07-31T18:08:47Z", "likes_count": 4}, {"comment_by": "Haziq Haq", "comment_text": "Who else is here because they are searching for his last moments \ud83d\ude25\ud83d\ude23", "comment_date": "2019-07-31T18:03:12Z", "likes_count": 21}, {"comment_by": "Dhany", "comment_text": "Rip", "comment_date": "2019-07-31T16:55:37Z", "likes_count": 0}, {"comment_by": "Rythen", "comment_text": "R.I.P I always loved your videos", "comment_date": "2019-07-31T15:55:58Z", "likes_count": 3}, {"comment_by": "Leafy2x", "comment_text": "Who else came here to see his last video he was in", "comment_date": "2019-07-31T10:51:11Z", "likes_count": 484}, {"comment_by": "Kerstin", "comment_text": "Rest in peace", "comment_date": "2019-07-31T08:15:35Z", "likes_count": 8}, {"comment_by": "BartekP42", "comment_text": "RIP...", "comment_date": "2019-07-31T07:27:13Z", "likes_count": 7}, {"comment_by": "Jake Hays", "comment_text": "Rip to the man who made all of our childhoods he will be missed\u2764\ufe0f", "comment_date": "2019-07-31T07:25:27Z", "likes_count": 17}, {"comment_by": "Matthew Becker", "comment_text": "May he RIP \u2764\ufe0f true legend", "comment_date": "2019-07-31T06:41:07Z", "likes_count": 12}, {"comment_by": "Isaiah Johnson", "comment_text": "May you Rest In Peace \ud83d\ude4f\ud83c\udffd", "comment_date": "2019-07-31T06:04:32Z", "likes_count": 7}, {"comment_by": "Wiqar Dream", "comment_text": "Inna lillahi wa inna ilaihi rajioon", "comment_date": "2019-07-31T04:56:15Z", "likes_count": 2}, {"comment_by": "Undead Wizard", "comment_text": "Rest in Peace", "comment_date": "2019-07-31T04:38:07Z", "likes_count": 6}, {"comment_by": "wafeeq ahmed", "comment_text": "Rip", "comment_date": "2019-07-31T04:06:31Z", "likes_count": 6}, {"comment_by": "Kevin", "comment_text": "R.I.P", "comment_date": "2019-07-31T03:59:26Z", "likes_count": 6}, {"comment_by": "Nate Hoang", "comment_text": "I MISS U SO MUCH IM IN TEARS RN I WATCHED U FOR SO LONG AND TO HEAR U PASSED\ud83d\ude2d\ud83d\ude2d\ud83d\ude2dTF MAN \ud83d\ude2d\ud83d\ude2d", "comment_date": "2019-07-31T03:58:16Z", "likes_count": 27}, {"comment_by": "Gud_Soup69 ", "comment_text": "RIP \ud83d\ude14\ud83d\ude2d", "comment_date": "2019-07-31T03:24:31Z", "likes_count": 6}, {"comment_by": "John Myers", "comment_text": "This is grants last video...", "comment_date": "2019-07-31T02:47:24Z", "likes_count": 194}, {"comment_by": "Xuei", "comment_text": "Rest in peace.", "comment_date": "2019-07-31T01:58:28Z", "likes_count": 8}, {"comment_by": "Whale Cat", "comment_text": "R.i.p", "comment_date": "2019-07-31T01:32:58Z", "likes_count": 2}, {"comment_by": "Blame Disney", "comment_text": "Rip", "comment_date": "2019-07-30T22:41:49Z", "likes_count": 7}, {"comment_by": "Solunetic", "comment_text": "RIP dude.. idk what to say.. I&#39;m..  crying", "comment_date": "2019-07-30T22:31:01Z", "likes_count": 69}, {"comment_by": "Cptain.Fine", "comment_text": "R. I. P", "comment_date": "2019-07-30T22:13:45Z", "likes_count": 5}, {"comment_by": "Angel Garcir", "comment_text": "Last Gordon video \ud83e\udd7a", "comment_date": "2019-07-30T22:13:28Z", "likes_count": 7}, {"comment_by": "Bigg bans Beats", "comment_text": "RIP \ud83d\ude22\ud83d\ude29\ud83d\ude4f", "comment_date": "2019-07-30T21:49:25Z", "likes_count": 18}, {"comment_by": "VALLEY", "comment_text": "&lt;3 in loving memory of grant, this is the last episode i can see with him in the thumbnail and the video &lt;3", "comment_date": "2019-07-30T21:47:38Z", "likes_count": 466}, {"comment_by": "Aidan Walker", "comment_text": "Rip still can&#39;t believe it", "comment_date": "2019-07-30T21:46:33Z", "likes_count": 16}, {"comment_by": "HeyItsSlayer", "comment_text": "Rest in peace brother, you shaped my childhood", "comment_date": "2019-07-30T21:27:41Z", "likes_count": 150}, {"comment_by": "Alex Air Conditioning", "comment_text": "Where did this legend go?", "comment_date": "2019-07-08T07:37:41Z", "likes_count": 0}, {"comment_by": "hxwklol", "comment_text": "June of 2019 or after gang wya", "comment_date": "2019-06-21T19:47:09Z", "likes_count": 0}, {"comment_by": "Directioner315", "comment_text": "I\u2019m going though the videos to see if the real king is in any of them", "comment_date": "2019-05-22T13:33:49Z", "likes_count": 0}, {"comment_by": "TridStar017", "comment_text": "What happened to the true king of random?", "comment_date": "2019-05-12T05:42:48Z", "likes_count": 0}, {"comment_by": "Moody Noodle", "comment_text": "Hey guys today we\u2019re making some self freezing soda for a cool summertime snack<br><br><br><br>Ig time change", "comment_date": "2019-04-30T04:52:53Z", "likes_count": 0}, {"comment_by": "Ms.BraveHeart", "comment_text": "What happened to that dude?", "comment_date": "2019-04-22T02:53:01Z", "likes_count": 0}, {"comment_by": "pastel_JLB ps4", "comment_text": "2019 anyone", "comment_date": "2019-04-16T19:10:25Z", "likes_count": 0}, {"comment_by": "qvshadow spirt", "comment_text": "who else watched it cuz of the true king of random at the start?", "comment_date": "2019-03-04T07:51:41Z", "likes_count": 385}, {"comment_by": "serenity17 pro", "comment_text": "I like this compilation", "comment_date": "2019-02-28T23:55:21Z", "likes_count": 0}, {"comment_by": "Rayan Haq", "comment_text": "Do a copper wire train tunnel with battery", "comment_date": "2019-02-26T02:02:38Z", "likes_count": 0}, {"comment_by": "Bone Lee", "comment_text": "Why don\u2019t you do your own videos anymore?", "comment_date": "2019-02-25T23:27:31Z", "likes_count": 0}, {"comment_by": "Brianna Coutts", "comment_text": "What about carbonated gummy candy?", "comment_date": "2019-02-24T01:45:13Z", "likes_count": 0}, {"comment_by": "Finn Cree", "comment_text": "Can u make fizzy ice", "comment_date": "2019-02-23T21:02:45Z", "likes_count": 0}, {"comment_by": "RASHADBAB", "comment_text": "Can u make edible slime", "comment_date": "2019-02-22T22:20:46Z", "likes_count": 0}, {"comment_by": "jantz bass", "comment_text": "what happens if you boil liquid nitrogen over the stove", "comment_date": "2019-02-21T13:14:16Z", "likes_count": 0}, {"comment_by": "\uc2a4\ud0c0\ub9ac\uc18c\uc601[StarrySoyoung]", "comment_text": "<del>TheKingOfRandom</del> <del>The</del> <del>King</del> <del>Of</del> <del>Random</del>", "comment_date": "2019-02-17T00:51:47Z", "likes_count": 1}, {"comment_by": "Hailey Ross", "comment_text": "You guys should try coloring clear resin with different makeup items", "comment_date": "2019-02-17T00:33:24Z", "likes_count": 0}, {"comment_by": "Robert Calbreath", "comment_text": "Can you guys make a mini waterfall with melted brass", "comment_date": "2019-02-15T00:59:29Z", "likes_count": 0}, {"comment_by": "LJ Awkward", "comment_text": "What happens if you keep your body submerged for days. I mean yeah you prune up but what else would happen to your body", "comment_date": "2019-02-14T15:08:54Z", "likes_count": 0}, {"comment_by": "Robert Ouellette", "comment_text": "We&#39;re do you get the liquid nitrogen from", "comment_date": "2019-02-14T04:11:58Z", "likes_count": 0}, {"comment_by": "Alexandra Zhuravlev", "comment_text": "Can you make a cast of Callie\u2019s face in cement and the try melting aluminum foil and pour that in the mold?<br><br><br>(Like if agree)", "comment_date": "2019-02-14T03:35:27Z", "likes_count": 0}, {"comment_by": "Eric Chugg", "comment_text": "Easiest way to purify water, both fresh and salt water?\u00a0 I would love a video on this.\u00a0 Thanks :-)", "comment_date": "2019-02-14T02:34:29Z", "likes_count": 0}, {"comment_by": "crispy leaf", "comment_text": "You should break a prince ruperd drop in water", "comment_date": "2019-02-13T21:31:18Z", "likes_count": 0}, {"comment_by": "Muhammet Cakmak", "comment_text": "What happens when u mix slime with burning part of match and burn?", "comment_date": "2019-02-13T18:27:08Z", "likes_count": 0}, {"comment_by": "Gannon BAG", "comment_text": "Dam this guy is genuinely pretty cool. I like the tabletop stove thing and the foil rockets lol.", "comment_date": "2019-02-13T12:09:07Z", "likes_count": 1}, {"comment_by": "Aiden Futa", "comment_text": "Make a slingshot with only using tools worth 10 dollars", "comment_date": "2019-02-13T11:58:04Z", "likes_count": 0}, {"comment_by": "Hasip Guner", "comment_text": "\u0130 did the translation to turkish", "comment_date": "2019-02-13T11:13:18Z", "likes_count": 0}, {"comment_by": "Buffalo", "comment_text": "who eats their ice cream cone like that..", "comment_date": "2019-02-13T08:42:16Z", "likes_count": 0}, {"comment_by": "Dustin Galkowski", "comment_text": "can you cook by freezing?", "comment_date": "2019-02-13T04:35:45Z", "likes_count": 0}, {"comment_by": "Fireskullegal", "comment_text": "Please include these in the next video try freeze drying orbeez and freeze dry printer ink", "comment_date": "2019-02-13T03:41:08Z", "likes_count": 0}, {"comment_by": "Cloudy Studios", "comment_text": "I thought you where dead", "comment_date": "2019-02-13T00:29:02Z", "likes_count": 0}, {"comment_by": "MitchellStem_50", "comment_text": "You should make fizzy ice cream freeze dry it then do taste test", "comment_date": "2019-02-12T23:14:48Z", "likes_count": 0}, {"comment_by": "Tetard Foo", "comment_text": "It\u2019s rewind time", "comment_date": "2019-02-12T23:02:53Z", "likes_count": 0}, {"comment_by": "whose this", "comment_text": "You should freeze drie apples and oranges see how they compare", "comment_date": "2019-02-12T22:53:06Z", "likes_count": 0}, {"comment_by": "ayead bin alam Shaishab", "comment_text": "Can we use liquid nitrogen to cool down CPU", "comment_date": "2019-02-12T22:22:37Z", "likes_count": 1}, {"comment_by": "TT Playz/Vlogs", "comment_text": "What would happen if you put a speaker in a vacuum chamber", "comment_date": "2019-02-12T21:59:19Z", "likes_count": 0}, {"comment_by": "Trooper the boxer", "comment_text": "Love the rewinds miss those type of experiments", "comment_date": "2019-02-12T21:40:25Z", "likes_count": 0}, {"comment_by": "mystic_golor", "comment_text": "What happens if you put blue tack into a vacuum chamber all you may try and make a rope outfit?", "comment_date": "2019-02-12T21:35:52Z", "likes_count": 1}, {"comment_by": "Melissa Burdan Schmitz", "comment_text": "Can you make a ball of magnesium the light on fire and throw it at something", "comment_date": "2019-02-12T21:35:52Z", "likes_count": 1}, {"comment_by": "\ud83c\udccfPLAYBOI\ud83c\udccf", "comment_text": "try putting liquid nitrogen over some lava", "comment_date": "2019-02-12T21:29:50Z", "likes_count": 0}, {"comment_by": "Ancientelixir 1", "comment_text": "If you made water extremely salty. How long would it take to freeze with and without Liquid Nitrogen. Plus what would it do in a vacuum chamber?", "comment_date": "2019-02-12T20:55:00Z", "likes_count": 0}, {"comment_by": "2CookieCat Sisters", "comment_text": "An idea for another video is you can use melted gallium and put it in a vacuum chamber.", "comment_date": "2019-02-12T20:54:09Z", "likes_count": 0}, {"comment_by": "Marko Rakun", "comment_text": "i heard that if you put hot watter and then frezze it  It will freeze faster then cold water...try it :)", "comment_date": "2019-02-12T20:46:18Z", "likes_count": 0}, {"comment_by": "Todd bradshaw", "comment_text": "Can you put a popped bag of popcorn in a dehydrater and chewed gum", "comment_date": "2019-02-12T20:35:29Z", "likes_count": 0}, {"comment_by": "Lucky Owl", "comment_text": "You can make a rope from paper?", "comment_date": "2019-02-12T20:34:16Z", "likes_count": 0}, {"comment_by": "Hi Hi", "comment_text": "Do a how to make a vacuum chamber video", "comment_date": "2019-02-12T20:27:50Z", "likes_count": 0}, {"comment_by": "D1BAB", "comment_text": "What if you put water in a vacuum chamber to get all the air out and then freeze it while still holding vacuum. Would it freeze with no air bubbles?", "comment_date": "2019-02-12T20:21:00Z", "likes_count": 0}, {"comment_by": "Eldi Musaj", "comment_text": "Try make a mold using super glue and baking soda", "comment_date": "2019-02-12T20:12:57Z", "likes_count": 0}, {"comment_by": "filip theis", "comment_text": "ITS rewind time", "comment_date": "2019-02-12T20:08:57Z", "likes_count": 0}, {"comment_by": "MasonBurger", "comment_text": "Can you do some experiments with calcium citrate and sodium alginate?", "comment_date": "2019-02-12T20:08:09Z", "likes_count": 1}, {"comment_by": "Strafe", "comment_text": "Make a rope with leaves.", "comment_date": "2019-02-12T19:51:51Z", "likes_count": 1}, {"comment_by": "Strafe", "comment_text": "Make a rope with notebook paper.", "comment_date": "2019-02-12T19:51:46Z", "likes_count": 3}, {"comment_by": "Strafe", "comment_text": "Make a rope with chip wood.", "comment_date": "2019-02-12T19:51:34Z", "likes_count": 1}, {"comment_by": "Strafe", "comment_text": "Make a rope with chip bags.", "comment_date": "2019-02-12T19:51:29Z", "likes_count": 1}, {"comment_by": "K then", "comment_text": "Can you do R-candy and thermite. Pls don&#39;t say pls, just say please", "comment_date": "2019-02-12T19:43:27Z", "likes_count": 0}, {"comment_by": "Shamacoo", "comment_text": "can you make a rocket with flour", "comment_date": "2019-02-12T19:33:22Z", "likes_count": 0}, {"comment_by": "rishabh kumar", "comment_text": "How much force does it take to rip apart or break two phone books which are tightly interlocked", "comment_date": "2019-02-12T19:32:42Z", "likes_count": 0}, {"comment_by": "Panda Kitten625", "comment_text": "What would happen if you boiled stuff, like liquid nitrogen and slime", "comment_date": "2019-02-12T19:30:31Z", "likes_count": 0}, {"comment_by": "Jos\u00e9 L\u00f3pez", "comment_text": "Could you try to make your own scented wax?", "comment_date": "2019-02-12T19:21:01Z", "likes_count": 0}, {"comment_by": "Brodie Twadelle", "comment_text": "Can you make a video on nerds(the candy) with a series of experiments <br><br>Off the top of my head you could powerderize, tumble etc", "comment_date": "2019-02-12T18:53:45Z", "likes_count": 0}, {"comment_by": "Susie Liu", "comment_text": "try boiling instant snow", "comment_date": "2019-02-12T18:49:31Z", "likes_count": 1}, {"comment_by": "Void", "comment_text": "Fill a balloon with helium and another one with sulfur hexafluoride and tie the together a a string! See what happens!", "comment_date": "2019-02-12T18:39:59Z", "likes_count": 1}, {"comment_by": "Malaine Touray", "comment_text": "Put dry ice in a vacuum chamber", "comment_date": "2019-02-12T18:39:03Z", "likes_count": 0}, {"comment_by": "Roman Dirscherl", "comment_text": "Put mercury on a clean aluminiumplate", "comment_date": "2019-02-12T18:24:12Z", "likes_count": 1}, {"comment_by": "I dans La roche", "comment_text": "can you dehydrate soap to see if it makes a soap bar", "comment_date": "2019-02-12T18:19:53Z", "likes_count": 1}, {"comment_by": "Abru van Zyl", "comment_text": "Wat happens when you spray your hole body with neverwet and then jump in a swimmingpool", "comment_date": "2019-02-12T17:59:13Z", "likes_count": 0}, {"comment_by": "Pragyan Sinha", "comment_text": "Make paper from scratch or try to conduct electricity from molten metal", "comment_date": "2019-02-12T17:52:23Z", "likes_count": 0}, {"comment_by": "Kyle Harris", "comment_text": "Launch 55 gallon drums with calcium carbide and water.", "comment_date": "2019-02-12T17:44:39Z", "likes_count": 0}, {"comment_by": "Ants in my Pants", "comment_text": "When you have water bellow 0\u00b0C and you put it on ice it Turks into ice can you try this with liquid nitrogen?\ud83d\ude1c", "comment_date": "2019-02-12T17:25:26Z", "likes_count": 0}, {"comment_by": "Gus The Goose", "comment_text": "It rewind time", "comment_date": "2019-02-12T17:11:35Z", "likes_count": 0}, {"comment_by": "Blastingblue Alex", "comment_text": "Try putting an egg in liquid nitrogen", "comment_date": "2019-02-12T17:05:00Z", "likes_count": 0}, {"comment_by": "Bega", "comment_text": "<a href=\"https://www.youtube.com/watch?v=n7xg7OZHqKs&amp;t=2m36s\">2:36</a> when you get killed in TTT", "comment_date": "2019-02-12T16:35:36Z", "likes_count": 0}, {"comment_by": "kkolio0001", "comment_text": "Can you make a incubator for chicken eggs", "comment_date": "2019-02-12T16:24:40Z", "likes_count": 0}, {"comment_by": "Ketorau", "comment_text": "Hey King Of Random Do U Think You can Make kiritos sword from sword art online and show us how to make it like so he can see", "comment_date": "2019-02-12T16:16:05Z", "likes_count": 2}, {"comment_by": "Rumi", "comment_text": "You should do some experiments with bismuth! Its a very cool metal.", "comment_date": "2019-02-12T16:13:14Z", "likes_count": 0}, {"comment_by": "Great Scott", "comment_text": "Try freezing your saliva in liquid nitrogen", "comment_date": "2019-02-12T16:13:05Z", "likes_count": 0}, {"comment_by": "Isaac Bjork", "comment_text": "You should see if you can grow a plant upside down", "comment_date": "2019-02-12T16:02:31Z", "likes_count": 0}, {"comment_by": "Oliver Chapman", "comment_text": "Can you turn grapes into raisins", "comment_date": "2019-02-12T15:59:26Z", "likes_count": 0}, {"comment_by": "Hzllnut", "comment_text": "How to make TNT?", "comment_date": "2019-02-12T15:49:43Z", "likes_count": 0}, {"comment_by": "jakelonghair", "comment_text": "Can you try cutting dry ice to coin size an using it in a vending machine to see if you can get something for free", "comment_date": "2019-02-12T15:25:35Z", "likes_count": 1}, {"comment_by": "Liebherr_", "comment_text": "Can you do Nitrogen Triodide tutorial?", "comment_date": "2019-02-12T15:14:49Z", "likes_count": 0}, {"comment_by": "Crazxy_D3xter", "comment_text": "Can you dehydrate toothpaste and then re-hydrate it, and then will it work the same?", "comment_date": "2019-02-12T15:13:07Z", "likes_count": 0}, {"comment_by": "Bayan Hamado", "comment_text": "Love you vids pls put ice cream in a vacuum Cameber", "comment_date": "2019-02-12T15:05:58Z", "likes_count": 0}, {"comment_by": "Baraa Elgamal", "comment_text": "What will happen to wood in a microwave ?", "comment_date": "2019-02-12T15:03:17Z", "likes_count": 0}, {"comment_by": "phantom physics", "comment_text": "make clear edible slime", "comment_date": "2019-02-12T14:58:45Z", "likes_count": 0}, {"comment_by": "Riyanka123", "comment_text": "what happens when you put dry ice in vacuum?", "comment_date": "2019-02-12T14:37:30Z", "likes_count": 0}, {"comment_by": "Riyanka123", "comment_text": "what happens if you put an egg in vacuum?", "comment_date": "2019-02-12T14:36:54Z", "likes_count": 0}, {"comment_by": "Barbara Zhang", "comment_text": "The reason I was here was because I wanted to make slime and this video on how to make magic mud came up and now I&#39;ve been here for like two years and oh boy do I miss those weekly projects!", "comment_date": "2019-02-12T14:36:12Z", "likes_count": 0}, {"comment_by": "Widowslovesapple", "comment_text": "Put blood in a vacation Camber", "comment_date": "2019-02-12T14:30:40Z", "likes_count": 0}, {"comment_by": "Aktiv8", "comment_text": "Here\u2019s something cool to try. What happens if you put foil in a hydraulic press? How much stronger would it be?", "comment_date": "2019-02-12T14:21:50Z", "likes_count": 3}, {"comment_by": "NAMITA SATAPATHY", "comment_text": "can you make a glass iron man helmet ?", "comment_date": "2019-02-12T14:02:02Z", "likes_count": 0}, {"comment_by": "diettocoke", "comment_text": "What will happen if u take dry ice to a bowl and put soap in it?", "comment_date": "2019-02-12T13:40:28Z", "likes_count": 0}, {"comment_by": "Noah Inman", "comment_text": "Y\u2019all should try dropping red hot metal into liquid nitrogen", "comment_date": "2019-02-12T13:20:47Z", "likes_count": 0}, {"comment_by": "DoTe", "comment_text": "Now your getting a bit nostalgic", "comment_date": "2019-02-12T13:13:04Z", "likes_count": 0}, {"comment_by": "unknown", "comment_text": "Can you make coke-a-melon?", "comment_date": "2019-02-12T13:02:16Z", "likes_count": 0}, {"comment_by": "Saif Hassan", "comment_text": "What happen if you put an egg in a vacuum chamber?", "comment_date": "2019-02-12T12:51:04Z", "likes_count": 0}, {"comment_by": "Rhys Williams-Ball", "comment_text": "I\u2019m kinda intrigued to see just how big the biggest air bazooka you guys could make would be\ud83d\ude02", "comment_date": "2019-02-12T12:47:58Z", "likes_count": 0}, {"comment_by": "GolfGaming", "comment_text": "Please mix carbonated vanilla ice cream and flat root beer", "comment_date": "2019-02-12T12:30:18Z", "likes_count": 0}, {"comment_by": "Meiru", "comment_text": "I got baited by Grant&#39;s face.<br>But tis only a rewind :(", "comment_date": "2019-02-12T12:23:59Z", "likes_count": 198}, {"comment_by": "Voltrix", "comment_text": "what will happen if you throw fire or heat resistance objects in a very hot object", "comment_date": "2019-02-12T12:17:54Z", "likes_count": 0}, {"comment_by": "Brycen", "comment_text": "Could you please put slime in some asid if that\u2019s spelt right\ud83d\ude22", "comment_date": "2019-02-12T11:46:58Z", "likes_count": 0}, {"comment_by": "Stuff About Stuff", "comment_text": "Damm King of random you post a video in every few hours keep up your great job", "comment_date": "2019-02-12T11:45:13Z", "likes_count": 0}, {"comment_by": "Ali", "comment_text": "pouring molten metal in liquid nitrogen", "comment_date": "2019-02-12T11:37:03Z", "likes_count": 0}, {"comment_by": "Linus Allarud", "comment_text": "Can you make colors/paint/dyes from Vegetables/fruits/plants?", "comment_date": "2019-02-12T11:34:37Z", "likes_count": 0}, {"comment_by": "amatsukrab 12", "comment_text": "YaAaAaaAgh its rewind time", "comment_date": "2019-02-12T11:28:10Z", "likes_count": 1}, {"comment_by": "uchihalite", "comment_text": "Make methonol and boric acid react with each otherand also methonol with lithium", "comment_date": "2019-02-12T11:27:28Z", "likes_count": 0}, {"comment_by": "Luka Luhtanen", "comment_text": "where is he btw", "comment_date": "2019-02-12T10:56:56Z", "likes_count": 0}, {"comment_by": "Caaaaa", "comment_text": "<b>It&#39;s</b> <b>random</b> <b>time</b>", "comment_date": "2019-02-12T10:02:37Z", "likes_count": 0}, {"comment_by": "jagveer Kapoor", "comment_text": "What will happen to  poly styrene if you  dip it into superglue", "comment_date": "2019-02-12T10:02:15Z", "likes_count": 0}, {"comment_by": "Minh Pham", "comment_text": "Can you put aluminum sheet in the furnace then melt it and craft it into something", "comment_date": "2019-02-12T09:50:25Z", "likes_count": 0}, {"comment_by": "Poohkie", "comment_text": "ERASABLE INK! Can you experiment with erasable ink and see if you can make it disappear when there is a bowl filled with it. Since it disappears while exposed to heat.", "comment_date": "2019-02-12T09:37:08Z", "likes_count": 0}, {"comment_by": "Teccy", "comment_text": "The slime go in the water<br>Slime is slimy and water is wet<br>(~_^)", "comment_date": "2019-02-12T09:34:30Z", "likes_count": 1}, {"comment_by": "Bryan Zavala", "comment_text": "Plsss like the post before this so they could see it", "comment_date": "2019-02-12T09:28:11Z", "likes_count": 0}, {"comment_by": "Bryan Zavala", "comment_text": "Can you make rope from a balloon", "comment_date": "2019-02-12T09:27:38Z", "likes_count": 0}, {"comment_by": "DraigoDragon", "comment_text": "liquid nitrogen meats dye colouring", "comment_date": "2019-02-12T09:18:52Z", "likes_count": 0}, {"comment_by": "Lauren B", "comment_text": "You guys should do a video competing to create and build a cool little box car or something.", "comment_date": "2019-02-12T09:01:54Z", "likes_count": 0}, {"comment_by": "Jonas Rabanal", "comment_text": "What happend when you put a dry ice on a alchol and will it syill light", "comment_date": "2019-02-12T08:51:00Z", "likes_count": 0}, {"comment_by": "Peggy White", "comment_text": "Will a firework go off if you put it in liquid nitrogen", "comment_date": "2019-02-12T08:36:31Z", "likes_count": 0}, {"comment_by": "Riyanka123", "comment_text": "what happens when you put pen ink in vaccum?", "comment_date": "2019-02-12T08:11:48Z", "likes_count": 0}, {"comment_by": "D Nooch", "comment_text": "What would happen if you took the goop from styrofoam, melted by acetone, and put it in a mold?", "comment_date": "2019-02-12T08:09:13Z", "likes_count": 0}, {"comment_by": "DRIFTs WOOD AND METAL WORK", "comment_text": "What happens when you blow up gas in water", "comment_date": "2019-02-12T08:08:20Z", "likes_count": 0}, {"comment_by": "Wezzy_networks S", "comment_text": "Hey guys! Got a suggestion for you <br>What happens when you put an aerogel in a vacuum chamber?", "comment_date": "2019-02-12T07:53:39Z", "likes_count": 0}, {"comment_by": "_itsbryxxn_ _eli_", "comment_text": "What happens if you cast iron in wood", "comment_date": "2019-02-12T07:44:10Z", "likes_count": 0}, {"comment_by": "Enigmatic Ghost", "comment_text": "what does ink do in liquid nitrogen?", "comment_date": "2019-02-12T07:33:35Z", "likes_count": 0}, {"comment_by": "Vendetta", "comment_text": "You should try using the sand blaster on the heart?", "comment_date": "2019-02-12T07:31:08Z", "likes_count": 0}, {"comment_by": "grayem pepper", "comment_text": "Put out a bonfire with liquid nitrogen", "comment_date": "2019-02-12T07:27:38Z", "likes_count": 0}, {"comment_by": "Shaikh Salim", "comment_text": "Try to make slime using gasoline and burn it", "comment_date": "2019-02-12T07:11:24Z", "likes_count": 0}, {"comment_by": "SirMajesty Easyworld Science Channel", "comment_text": "Wow,that&#39;s quite interesting", "comment_date": "2019-02-12T06:57:17Z", "likes_count": 0}, {"comment_by": "TICO", "comment_text": "I\u2019m not trying to be hostile, and I know it\u2019s hard to come up with new ideas but I feel the end of TKOR is here. Just repetitive videos, lack of originality, and sometimes... just flat out unentertaining...<br>Please don\u2019t take this personally", "comment_date": "2019-02-12T06:51:50Z", "likes_count": 0}, {"comment_by": "Vinni2K", "comment_text": "I made my own rope last sunday.<br>I was so happy to see that i could to that :D", "comment_date": "2019-02-12T06:46:22Z", "likes_count": 0}, {"comment_by": "Ben Pickering", "comment_text": "I don\u2019t know if you have done this but what happens if you chuck cordial in the dehydrator?", "comment_date": "2019-02-12T06:45:38Z", "likes_count": 0}, {"comment_by": "Ayden Annala", "comment_text": "Liquid nitrogen vs hot tar?", "comment_date": "2019-02-12T06:37:07Z", "likes_count": 0}, {"comment_by": "vivek j dev", "comment_text": "What happen when heated diamond in drop in liquid oxygen", "comment_date": "2019-02-12T06:31:46Z", "likes_count": 0}, {"comment_by": "Manni's workshop", "comment_text": "Boil an EGG  take the shell out and put it in dehydrator", "comment_date": "2019-02-12T06:23:08Z", "likes_count": 2}, {"comment_by": "Catrinoiu Andrei", "comment_text": "Can you make edible slime?", "comment_date": "2019-02-12T06:18:39Z", "likes_count": 0}, {"comment_by": "Julian Mitchell", "comment_text": "Do duck tape rope", "comment_date": "2019-02-12T06:14:36Z", "likes_count": 0}, {"comment_by": "AlexanderTheGreat91", "comment_text": "What\u2019s with the letters and numbers that keep showing up in videos?", "comment_date": "2019-02-12T06:10:31Z", "likes_count": 0}, {"comment_by": "Tracy Hewes", "comment_text": "Y&#39;all should try to make castings with cement and what it&#39;d do in vacuum", "comment_date": "2019-02-12T06:06:07Z", "likes_count": 0}, {"comment_by": "Devam Jangra", "comment_text": "Nice experiment \ud83e\udd4a", "comment_date": "2019-02-12T05:54:57Z", "likes_count": 0}, {"comment_by": "AryanFromYT", "comment_text": "I wonder what would cotton candy do in liquid N2", "comment_date": "2019-02-12T05:53:13Z", "likes_count": 0}, {"comment_by": "Pushkar Kulkarni", "comment_text": "Its rewind was still, still!!! Better than 2018 youtube rewind", "comment_date": "2019-02-12T05:48:53Z", "likes_count": 1}, {"comment_by": "Santhanalakshmi Balaraman", "comment_text": "What happened to chewing gum on deep frying", "comment_date": "2019-02-12T05:48:02Z", "likes_count": 0}, {"comment_by": "W0lfram", "comment_text": "What happens if you microwave silly putty<br><br>What happens if you put silly putty in a vacuum  chamber <br><br>What happens if you boil silly putty/put it in liquid nitrogen", "comment_date": "2019-02-12T05:47:54Z", "likes_count": 0}, {"comment_by": "whau", "comment_text": "Et", "comment_date": "2019-02-12T05:47:50Z", "likes_count": 0}, {"comment_by": "Jonathon Kostiuk", "comment_text": "Somebody today made me ask myself if you could tan leather with Nutella??? I would love to see what you can tan leather with! haha", "comment_date": "2019-02-12T05:43:38Z", "likes_count": 0}, {"comment_by": "DJake", "comment_text": "Can you see what happens if you combine kinetic sand and a vacuum chamber?", "comment_date": "2019-02-12T05:30:49Z", "likes_count": 0}, {"comment_by": "Mama Kangaskhan Videos", "comment_text": "I kind of want to see what they can turn into a lollypop/sucker. We know tootsie rolls are great, but what else is there?", "comment_date": "2019-02-12T05:28:04Z", "likes_count": 0}, {"comment_by": "Beau Mantanona", "comment_text": "What if you microwaved a lit candle", "comment_date": "2019-02-12T05:24:36Z", "likes_count": 0}, {"comment_by": "Alex Mason", "comment_text": "Can you make rope from shoe laces the sweets but make a cast like a pip and the girth the size of your hand  and do that 3 times", "comment_date": "2019-02-12T05:22:29Z", "likes_count": 1}, {"comment_by": "Shima the fox", "comment_text": "Next time you guys try breaking car windows, you should try video game strategies", "comment_date": "2019-02-12T05:13:13Z", "likes_count": 1}, {"comment_by": "The Bricker", "comment_text": "Where did you get the name TKOR it is cool, It\u2019s the random is it it", "comment_date": "2019-02-12T05:11:39Z", "likes_count": 0}, {"comment_by": "Tiana Byrd", "comment_text": "You guys should try soap, dry ice and water then see what will happen when you put different things in it?,also what will happen if you pour it out in a very cold climate.", "comment_date": "2019-02-12T05:02:51Z", "likes_count": 0}, {"comment_by": "Colby Christopherson", "comment_text": "The number of dislikes on this comment is your IQ", "comment_date": "2019-02-12T05:00:59Z", "likes_count": 0}, {"comment_by": "Ma Lao", "comment_text": "Pour Molten Glass onto Dry Ice", "comment_date": "2019-02-12T04:57:05Z", "likes_count": 0}, {"comment_by": "faboleo", "comment_text": "try breaking a car bullet proof glass", "comment_date": "2019-02-12T04:51:51Z", "likes_count": 0}, {"comment_by": "Ewan Ward", "comment_text": "Can you do a DIY laser pointer video pls?", "comment_date": "2019-02-12T04:49:08Z", "likes_count": 0}, {"comment_by": "Justin Manning", "comment_text": "What would happen if you put sulfur hexafluoride in water? Would it sink to the bottom?", "comment_date": "2019-02-12T04:45:10Z", "likes_count": 0}, {"comment_by": "g3rmz47", "comment_text": "You should make this comment into a rope by printing out this comment a million times filing it together and doing that rope process", "comment_date": "2019-02-12T04:45:07Z", "likes_count": 0}, {"comment_by": "XxdragonFierxX", "comment_text": "Can wood melt?", "comment_date": "2019-02-12T04:40:42Z", "likes_count": 0}, {"comment_by": "Kerie Barnett", "comment_text": "What is the melting point of glass and can to try to make some", "comment_date": "2019-02-12T04:40:32Z", "likes_count": 0}, {"comment_by": "Slimebelly", "comment_text": "Persist.", "comment_date": "2019-02-12T04:38:42Z", "likes_count": 0}, {"comment_by": "YoussGm3o8", "comment_text": "Can I get 700 subscribers pls?", "comment_date": "2019-02-12T04:33:42Z", "likes_count": 1}, {"comment_by": "Beck Vermilion", "comment_text": "You should put a teddy bear in the vacuum chamber", "comment_date": "2019-02-12T04:32:28Z", "likes_count": 3}, {"comment_by": "UAV freedom", "comment_text": "Hi guy pls try to carbonate pancakes", "comment_date": "2019-02-12T04:30:46Z", "likes_count": 0}, {"comment_by": "ThatSpaceNerd", "comment_text": "Better than YouTube rewind", "comment_date": "2019-02-12T04:28:31Z", "likes_count": 0}, {"comment_by": "Camden Henderson", "comment_text": "Freeze dry wet floral foam please.", "comment_date": "2019-02-12T04:27:43Z", "likes_count": 0}, {"comment_by": "Aydin Smith", "comment_text": "Can you make the cathode ray tube into a ray gun?", "comment_date": "2019-02-12T04:15:25Z", "likes_count": 0}, {"comment_by": "TandM bros", "comment_text": "Make your own car tire. Like some type of squshy wheel that takes bumps well but not the honey comb tire.", "comment_date": "2019-02-12T04:11:44Z", "likes_count": 0}, {"comment_by": "Anti Universe", "comment_text": "Can you make pop rock candy", "comment_date": "2019-02-12T04:09:38Z", "likes_count": 1}, {"comment_by": "Joplan Crala", "comment_text": "You should make some Biodiesel or Ethanol.", "comment_date": "2019-02-12T03:58:37Z", "likes_count": 0}, {"comment_by": "Billiam Reviews", "comment_text": "You guys should use magnetite powder in the sandblaster", "comment_date": "2019-02-12T03:57:25Z", "likes_count": 0}, {"comment_by": "woshieman 2", "comment_text": "a", "comment_date": "2019-02-12T03:51:33Z", "likes_count": 0}, {"comment_by": "woshieman 2", "comment_text": "a", "comment_date": "2019-02-12T03:51:30Z", "likes_count": 0}, {"comment_by": "woshieman 2", "comment_text": "d", "comment_date": "2019-02-12T03:51:23Z", "likes_count": 0}, {"comment_by": "woshieman 2", "comment_text": "d", "comment_date": "2019-02-12T03:51:21Z", "likes_count": 0}, {"comment_by": "woshieman 2", "comment_text": "d", "comment_date": "2019-02-12T03:51:14Z", "likes_count": 0}, {"comment_by": "woshieman 2", "comment_text": "d", "comment_date": "2019-02-12T03:51:12Z", "likes_count": 0}, {"comment_by": "woshieman 2", "comment_text": "h", "comment_date": "2019-02-12T03:51:08Z", "likes_count": 0}, {"comment_by": "woshieman 2", "comment_text": "e", "comment_date": "2019-02-12T03:51:05Z", "likes_count": 0}, {"comment_by": "ImInfinitz", "comment_text": "What happens when you pour liquid nitrogen into melted candle wax", "comment_date": "2019-02-12T03:48:51Z", "likes_count": 0}, {"comment_by": "LaunaLove", "comment_text": "Super glue into slime?!!?", "comment_date": "2019-02-12T03:47:12Z", "likes_count": 0}, {"comment_by": "Sauls XS 2", "comment_text": "This is the 4 year anniversary of the king o random", "comment_date": "2019-02-12T03:44:14Z", "likes_count": 0}, {"comment_by": "TimiderWeevil90", "comment_text": "What would happen if you mixed gasoline and the powder from a fire extinguisher", "comment_date": "2019-02-12T03:35:15Z", "likes_count": 0}, {"comment_by": "paredes annie", "comment_text": "Can you extract dna from different fruits", "comment_date": "2019-02-12T03:30:58Z", "likes_count": 0}, {"comment_by": "milena galloway", "comment_text": "What would happen if you put acetone in a vacuum chamber?", "comment_date": "2019-02-12T03:27:25Z", "likes_count": 0}, {"comment_by": "Bandit Pastry", "comment_text": "Umm freeze", "comment_date": "2019-02-12T03:23:20Z", "likes_count": 1}, {"comment_by": "Delta -", "comment_text": "What does it look like when you freeze rain water?", "comment_date": "2019-02-12T03:21:49Z", "likes_count": 0}, {"comment_by": "Saksham Gupta", "comment_text": "Petrol in nitrogen", "comment_date": "2019-02-12T03:20:46Z", "likes_count": 1}, {"comment_by": "Mercedez Trinidad", "comment_text": "Or on dry ice", "comment_date": "2019-02-12T03:18:54Z", "likes_count": 0}, {"comment_by": "Mercedez Trinidad", "comment_text": "Can you put acetone in liquid nitrogen please", "comment_date": "2019-02-12T03:18:28Z", "likes_count": 0}, {"comment_by": "Tiger Games", "comment_text": "Grants alive?", "comment_date": "2019-02-12T03:17:24Z", "likes_count": 0}, {"comment_by": "vxmi", "comment_text": "Do a vid with the action lab", "comment_date": "2019-02-12T03:12:08Z", "likes_count": 1}, {"comment_by": "Pete life", "comment_text": "Do a Answer question video", "comment_date": "2019-02-12T03:09:34Z", "likes_count": 0}, {"comment_by": "Moises B", "comment_text": "I love you videos", "comment_date": "2019-02-12T03:09:03Z", "likes_count": 0}, {"comment_by": "Kyle Lum", "comment_text": "This is when TKOR was epic instructionals not experiments geared towards children", "comment_date": "2019-02-12T03:06:03Z", "likes_count": 0}, {"comment_by": "Bad Gamor", "comment_text": "Can you freeze mercury in liquid nitrogen", "comment_date": "2019-02-12T03:04:58Z", "likes_count": 0}, {"comment_by": "Scorpio Scythe", "comment_text": "Freeze, it freezes just like you would expect. I\u2019ll tell you if I\u2019m right in the comment below.", "comment_date": "2019-02-12T03:01:16Z", "likes_count": 0}, {"comment_by": "Super cool Jits", "comment_text": "Can you make a tissue rope", "comment_date": "2019-02-12T02:58:32Z", "likes_count": 0}, {"comment_by": "Hehe Hehe", "comment_text": "What does liqid nitro do in slime?????", "comment_date": "2019-02-12T02:55:34Z", "likes_count": 0}, {"comment_by": "Samuel Delgado", "comment_text": "Do bullets in liquid nitrogen!", "comment_date": "2019-02-12T02:49:13Z", "likes_count": 0}, {"comment_by": "Flowers Pic", "comment_text": "You guys should put squishy\u2019s and slime in a vacuum chamber", "comment_date": "2019-02-12T02:44:14Z", "likes_count": 0}, {"comment_by": "DoddO", "comment_text": "What Does Justin Y do in Liquid Nitrogen", "comment_date": "2019-02-12T02:41:45Z", "likes_count": 2}, {"comment_by": "Theguynooneknows", "comment_text": "Blow torch a bunch of peto bismo and you would get metal", "comment_date": "2019-02-12T02:40:47Z", "likes_count": 0}, {"comment_by": "iTechSavvy", "comment_text": "You should try to Melt down a ton of different kind of chocolate bars and make one monster chocolate bar! \ud83d\ude03", "comment_date": "2019-02-12T02:40:23Z", "likes_count": 0}, {"comment_by": "Jerry_ Jarvice420", "comment_text": "Can you freeze Mercury", "comment_date": "2019-02-12T02:27:25Z", "likes_count": 0}, {"comment_by": "Jacob Quirion", "comment_text": "Do an experiment to see if you can freeze alcohol", "comment_date": "2019-02-12T02:22:35Z", "likes_count": 0}, {"comment_by": "Defaulty Boi", "comment_text": "Make liquid nitrogen powered bottle rockets \ud83d\ude02", "comment_date": "2019-02-12T02:21:05Z", "likes_count": 0}, {"comment_by": "George", "comment_text": "Can you make a knife with aluminum foil?", "comment_date": "2019-02-12T02:11:07Z", "likes_count": 0}, {"comment_by": "Cohen Murphy", "comment_text": "What happens if you put sulphur hexafluoride and helium balloons in a vacuum chamber \ud83e\udd2f", "comment_date": "2019-02-12T02:06:49Z", "likes_count": 0}, {"comment_by": "kush killer", "comment_text": "This wasn&#39;t bite size enough, I think I bit more than I can chew", "comment_date": "2019-02-12T02:06:32Z", "likes_count": 0}, {"comment_by": "PCRT CIU", "comment_text": "In Chinese \u4f60\u7279\u5a18\u7684\u771f\u662f\u4e2a\u5929\u624d            \u270c(\u033f\u2580\u033f\u2009\u033f\u0139\u032f\u033f\u033f\u2580\u033f \u033f)\u270c", "comment_date": "2019-02-12T02:00:44Z", "likes_count": 0}, {"comment_by": "Adrianne Goans", "comment_text": "Can you freeze off a mole or wart using liquid nitrogen?", "comment_date": "2019-02-12T02:00:38Z", "likes_count": 0}, {"comment_by": "Anna Robinson", "comment_text": "You should try following a 5 minute craft or troom troom video", "comment_date": "2019-02-12T01:59:46Z", "likes_count": 0}, {"comment_by": "Protocol Syren", "comment_text": "U guys should find the weakest rope or twin and try to make it stronger than the bottle rope", "comment_date": "2019-02-12T01:57:46Z", "likes_count": 0}, {"comment_by": "Andrew Felix Ferdaus", "comment_text": "I don\u2019t know, you ask rimuru", "comment_date": "2019-02-12T01:47:45Z", "likes_count": 0}, {"comment_by": "mancraft", "comment_text": "I always wondered if you could make a slime prince Rupert drop in liquid nitrogen and test it&#39;s strength", "comment_date": "2019-02-12T01:47:00Z", "likes_count": 0}, {"comment_by": "Kingcoalbro", "comment_text": "<a href=\"https://www.youtube.com/watch?v=n7xg7OZHqKs&amp;t=2m26s\">2:26</a> looks like meth I don\u2019t know what meth looks like but that\u2019s how I picture it and in gta", "comment_date": "2019-02-12T01:39:17Z", "likes_count": 0}, {"comment_by": "RAGEGOD 333", "comment_text": "I challenge you to run a generator  off of Grant&#39;s version of the hydrogen generator to power a small amount of home items", "comment_date": "2019-02-12T01:38:19Z", "likes_count": 1}, {"comment_by": "Zebra Playz", "comment_text": "Pizza in the dehydrator?", "comment_date": "2019-02-12T01:27:02Z", "likes_count": 0}, {"comment_by": "Splendours Vale", "comment_text": "Great mix!", "comment_date": "2019-02-12T01:19:55Z", "likes_count": 0}, {"comment_by": "Adam B", "comment_text": "can you make explosive bullets", "comment_date": "2019-02-12T01:16:05Z", "likes_count": 1}, {"comment_by": "Adam B", "comment_text": "can you make a video about turning earplugs into a squishy", "comment_date": "2019-02-12T01:15:35Z", "likes_count": 1}, {"comment_by": "kevin coones", "comment_text": "Put vinegar in liquid nitrogen. Along with baking Soda.", "comment_date": "2019-02-12T01:09:01Z", "likes_count": 0}, {"comment_by": "Blaize", "comment_text": "I kinda wish you did more videos.", "comment_date": "2019-02-12T01:05:58Z", "likes_count": 0}, {"comment_by": "Technical weapons", "comment_text": "friends please visit my chunnel why is not able monetization please help me friends please please please \ud83d\ude22\ud83d\ude22\ud83d\ude22\ud83d\ude22\ud83d\ude22\ud83d\ude22\ud83d\ude22\ud83d\ude22", "comment_date": "2019-02-12T01:05:41Z", "likes_count": 0}, {"comment_by": "weirdo 69", "comment_text": "uhhhh i think it freezes", "comment_date": "2019-02-12T00:55:42Z", "likes_count": 0}, {"comment_by": "Aiden Ko", "comment_text": "Tbh this is better than all the yt rewinds", "comment_date": "2019-02-12T00:46:05Z", "likes_count": 0}, {"comment_by": "Traveling Northish", "comment_text": "freeze dry slime or pickles", "comment_date": "2019-02-12T00:41:58Z", "likes_count": 0}, {"comment_by": "funy art star", "comment_text": "What will happen if you put coins in the heater????", "comment_date": "2019-02-12T00:36:48Z", "likes_count": 0}, {"comment_by": "Poke Dino", "comment_text": "You should try making water in a balloon \ud83c\udf88", "comment_date": "2019-02-12T00:36:36Z", "likes_count": 0}, {"comment_by": "silly_fishing_penguin", "comment_text": "What happens if you microwave c4", "comment_date": "2019-02-12T00:33:52Z", "likes_count": 0}, {"comment_by": "Ava Brophy", "comment_text": "What happens to slime when it heats up and gets put in dry ice", "comment_date": "2019-02-12T00:32:42Z", "likes_count": 0}, {"comment_by": "Corwin", "comment_text": "Can yall put cans of soda and other objects like that in the vacuum chamber?", "comment_date": "2019-02-12T00:26:31Z", "likes_count": 0}, {"comment_by": "Andre Cruz", "comment_text": "Make cardboard rope", "comment_date": "2019-02-12T00:24:57Z", "likes_count": 0}, {"comment_by": "Pip", "comment_text": "Ermm..... Kneaded erasers are cool.... Maybe try something with them?", "comment_date": "2019-02-12T00:23:57Z", "likes_count": 0}, {"comment_by": "Noah Spear", "comment_text": "Test to see if an RC helicopter can fly in a vacuum chamber", "comment_date": "2019-02-12T00:23:27Z", "likes_count": 0}, {"comment_by": "Cvalenx", "comment_text": "Hey king could you put a microphone up to a speaker and see what happends? (Sound Chain Reaction)", "comment_date": "2019-02-12T00:23:26Z", "likes_count": 0}, {"comment_by": "Law", "comment_text": "Can you plz make a stretchy ice cream plz", "comment_date": "2019-02-12T00:22:16Z", "likes_count": 0}, {"comment_by": "Raging Wasabi", "comment_text": "u clearly never watched konosuba season 2 final boss fight", "comment_date": "2019-02-12T00:19:50Z", "likes_count": 0}, {"comment_by": "MrShrimpy Gaming", "comment_text": "Hey Nate could you guys and gale melt lava rocks and see what metals you can melt then cast the King of Random logo with it", "comment_date": "2019-02-12T00:18:36Z", "likes_count": 0}, {"comment_by": "ekum rahal", "comment_text": "Can you show us how to make a EMP jammer", "comment_date": "2019-02-12T00:18:11Z", "likes_count": 0}, {"comment_by": "ANNALEXANDRA KROLOUND DEL'VALLE DAVINCCIE", "comment_text": "Now it&#39;s the king of random.. that the guy", "comment_date": "2019-02-12T00:17:24Z", "likes_count": 0}, {"comment_by": "Kareem Yakout", "comment_text": "What would happen if you put benzene or some sort of fuel in liquid nitrogen??", "comment_date": "2019-02-12T00:08:35Z", "likes_count": 0}, {"comment_by": "Corrie Sakowski", "comment_text": "What if you put LN2 in a microwave?", "comment_date": "2019-02-12T00:07:24Z", "likes_count": 0}, {"comment_by": "Leah Jazz", "comment_text": "Make a jello Heart for valentines day with strawberry coconut flavor and raspberry flavor then combine them together and try it. \ub538\uae30 \ucf54\ucf54\ub11b \ud5a5\uacfc \ub77c\uc988\ubca0\ub9ac \ud5a5\uacfc \ubc1c\ub80c\ud0c0\uc778 \ub370\uc774\ub97c\uc704\ud55c \uc824\ub9ac \ud558\ud2b8 \ub9cc\ub4e4\uae30\ub97c \ud55c\uaebc\ubc88\uc5d0 \uc2dc\ub3c4\ud574\ubcf4\uc2ed\uc2dc\uc624.", "comment_date": "2019-02-12T00:04:40Z", "likes_count": 0}, {"comment_by": "I like art.-. Tiktok", "comment_text": "You should try to make a hole in glass with a sand blaster", "comment_date": "2019-02-11T23:55:30Z", "likes_count": 0}, {"comment_by": "Unreliably Good", "comment_text": "Why are you guys doing this it&#39;s midway through February nobody wants to see video&#39;s they&#39;ve already watched If you guys don&#39;t have content just don&#39;t post for that day", "comment_date": "2019-02-11T23:54:39Z", "likes_count": 1}, {"comment_by": "cfv1984", "comment_text": "Guys we need to sit down and have a short chat.<br>You went from &quot;let&#39;s do this insanely fun if impractical thing and see what happens&quot; to &quot;is goop goopy? A scientific experiment minus the science&quot; and I&#39;m no longer as ok with it as i was.", "comment_date": "2019-02-11T23:54:29Z", "likes_count": 0}, {"comment_by": "Francis Dueck", "comment_text": "Try putting chocolate in the freeze drier and the vacuum chamber.", "comment_date": "2019-02-11T23:50:26Z", "likes_count": 0}, {"comment_by": "oaifasdf uha2wesdfjk", "comment_text": "Next time you should pour Liquid Nitrogen into a coal furnace!", "comment_date": "2019-02-11T23:49:51Z", "likes_count": 0}, {"comment_by": "Mitchell Walp", "comment_text": "Bio plastic please.", "comment_date": "2019-02-11T23:49:46Z", "likes_count": 0}, {"comment_by": "JC1OZ", "comment_text": "will cotton candy disovle trough a teddy bear", "comment_date": "2019-02-11T23:47:00Z", "likes_count": 0}, {"comment_by": "Glitchy M", "comment_text": "<b>The reason I started to love science</b>", "comment_date": "2019-02-11T23:46:06Z", "likes_count": 1}, {"comment_by": "1Braezy", "comment_text": "If Possible What\u2019s Bigger The Earth Or The Moon??\ud83e\udd14\ud83e\udd14", "comment_date": "2019-02-11T23:42:10Z", "likes_count": 0}, {"comment_by": "Quinn Cooper", "comment_text": "I have not watched you in a long time and I can\u2019t believe you are still doing experiments with liquid nitrogen!!!", "comment_date": "2019-02-11T23:40:32Z", "likes_count": 0}, {"comment_by": "Joseph Booe", "comment_text": "Match rockets a classic", "comment_date": "2019-02-11T23:36:27Z", "likes_count": 0}, {"comment_by": "MrGoodVibes", "comment_text": "Guys! I killed Marshmello in fortnite watch my latest video!", "comment_date": "2019-02-11T23:30:32Z", "likes_count": 0}, {"comment_by": "Galreus J", "comment_text": "what will happen if you combine (Calcium Carbide) with (Liquid Nitrogen) and if steam will be flammable like if you fire  (Calcium Carbide) and (watter) steam????", "comment_date": "2019-02-11T23:30:17Z", "likes_count": 0}, {"comment_by": "Devyn Bido", "comment_text": "Try to make homemade dry ice", "comment_date": "2019-02-11T23:29:36Z", "likes_count": 0}, {"comment_by": "Devyn Bido", "comment_text": "Put ice in the dehydrater", "comment_date": "2019-02-11T23:29:14Z", "likes_count": 0}, {"comment_by": "Maggie Vaughan", "comment_text": "This is the content I came here for, now it\u2019s only experiments", "comment_date": "2019-02-11T23:28:42Z", "likes_count": 0}, {"comment_by": "Nathen LEFFERT", "comment_text": "What happens if you put liquid nitrogen into oobleck", "comment_date": "2019-02-11T23:27:15Z", "likes_count": 0}, {"comment_by": "Luka Vandevort", "comment_text": "Can you make a mini version of a tornado", "comment_date": "2019-02-11T23:26:07Z", "likes_count": 0}, {"comment_by": "MercilessOce", "comment_text": "Put Oobleck in liquid nitrogen.", "comment_date": "2019-02-11T23:25:41Z", "likes_count": 0}, {"comment_by": "jgw246", "comment_text": "I&#39;m curious what would happen if you tried making cotton candy from cough drops or vitamin C drops", "comment_date": "2019-02-11T23:25:15Z", "likes_count": 0}, {"comment_by": "Alexandria Crayne", "comment_text": "I would love to see how to make a freeze dryer! Then use it to make astronaut icecream!", "comment_date": "2019-02-11T23:19:28Z", "likes_count": 1}, {"comment_by": "Roblox Minecraft gamer -0-", "comment_text": "I love this", "comment_date": "2019-02-11T23:17:44Z", "likes_count": 0}, {"comment_by": "Selvedin", "comment_text": "What would happen if you put gallium in the metal foundry???", "comment_date": "2019-02-11T23:14:27Z", "likes_count": 3}, {"comment_by": "Kiyocraft", "comment_text": "I&#39;m not going to   Be mean Right now Incase the editor is watching,Great job on these vidios, Beside nate,Actualy the girl Can we maKe Giant Realistic Astronot helmits with Nubs on Top?", "comment_date": "2019-02-11T23:12:45Z", "likes_count": 0}, {"comment_by": "Ali Hamid", "comment_text": "what happens when you mix mercury with anti freeze and then pour liquid nitrogen on it?", "comment_date": "2019-02-11T23:07:38Z", "likes_count": 0}, {"comment_by": "Dakota Linebaugh", "comment_text": "Hey TKOR can you guys make a table that looks like your logo but make it so awesome no one can compete. Huge fan keep up the vids.", "comment_date": "2019-02-11T23:05:25Z", "likes_count": 0}, {"comment_by": "Amanda Sekerke", "comment_text": "Lol i love you guys you inspired me to get off my computer and do some experiments", "comment_date": "2019-02-11T23:01:02Z", "likes_count": 0}, {"comment_by": "MEE7", "comment_text": "Can you make a gun? (Not to hurt anybody, obviously)", "comment_date": "2019-02-11T23:00:27Z", "likes_count": 2}, {"comment_by": "Chase Hunter", "comment_text": "How much can the human saliva dissolve", "comment_date": "2019-02-11T22:58:46Z", "likes_count": 0}, {"comment_by": "Bear with nice hair", "comment_text": "Oh no oh my gad ah owagskzb", "comment_date": "2019-02-11T22:57:26Z", "likes_count": 0}, {"comment_by": "Phantoms Dead inside", "comment_text": "I SMELL PENNIES......BURNING <a href=\"https://www.youtube.com/watch?v=n7xg7OZHqKs&amp;t=1m49s\">1:49</a>", "comment_date": "2019-02-11T22:57:22Z", "likes_count": 0}, {"comment_by": "Nick 19", "comment_text": "Who is grand ?", "comment_date": "2019-02-11T22:56:34Z", "likes_count": 0}, {"comment_by": "f4z0", "comment_text": "who is this guy?<br>Kappa", "comment_date": "2019-02-11T22:54:45Z", "likes_count": 0}, {"comment_by": "The_Dead_Knight3", "comment_text": "The only rewind I Wana see from last year", "comment_date": "2019-02-11T22:49:40Z", "likes_count": 0}, {"comment_by": "RaionKo", "comment_text": "Can u make Thor&#39;s axe", "comment_date": "2019-02-11T22:48:14Z", "likes_count": 0}, {"comment_by": "Miguel Angel Acosta", "comment_text": "Can you mold silicone in silly putty?", "comment_date": "2019-02-11T22:45:46Z", "likes_count": 1}, {"comment_by": "Miguel Angel Acosta", "comment_text": "What happens if you put glow stick fluid in orbeez?", "comment_date": "2019-02-11T22:45:34Z", "likes_count": 2}, {"comment_by": "Bell", "comment_text": "I know this place nearby that makes ice cream with liquid nitrogen", "comment_date": "2019-02-11T22:42:57Z", "likes_count": 0}, {"comment_by": "Henrik Heesch", "comment_text": "WOW", "comment_date": "2019-02-11T22:41:55Z", "likes_count": 0}, {"comment_by": "Daniel Weiss", "comment_text": "<a href=\"https://www.youtube.com/watch?v=n7xg7OZHqKs&amp;t=2m21s\">2:21</a> Oh, That&#39;s Hot, That&#39;s Hot.", "comment_date": "2019-02-11T22:41:10Z", "likes_count": 0}, {"comment_by": "Sparkle Duckies", "comment_text": "Dehydrate invisible ink pls", "comment_date": "2019-02-11T22:41:01Z", "likes_count": 0}, {"comment_by": "SharkZyOP Fan", "comment_text": "What does hot glue in liquid netrogeon", "comment_date": "2019-02-11T22:40:55Z", "likes_count": 0}, {"comment_by": "2HRS2PLAY", "comment_text": "Play with tesla coils", "comment_date": "2019-02-11T22:39:44Z", "likes_count": 0}, {"comment_by": "BigDroneFlyer1964", "comment_text": "I never thought about trying to freeze slime in LN2! :-O", "comment_date": "2019-02-11T22:38:44Z", "likes_count": 0}, {"comment_by": "ShrekFanboy 1", "comment_text": "What would happen if it met lava", "comment_date": "2019-02-11T22:37:47Z", "likes_count": 0}, {"comment_by": "WhippyMindo", "comment_text": "When drinking a fizzy cherry drink I have red/pink bubbles, try and make colourful bubbles", "comment_date": "2019-02-11T22:37:14Z", "likes_count": 0}, {"comment_by": "Robin De Jong", "comment_text": "Could you test if the saying sink like a lead Balloon doesn&#39;t have to be true. So basically try to make a flying lead balloon", "comment_date": "2019-02-11T22:36:36Z", "likes_count": 0}, {"comment_by": "ROOFKOR3AN", "comment_text": "Still better then the 2018 YT rewind", "comment_date": "2019-02-11T22:35:57Z", "likes_count": 5}, {"comment_by": "Fozan Khalid", "comment_text": "What will happen if you put liquidniteogen in obbleck", "comment_date": "2019-02-11T22:35:41Z", "likes_count": 0}, {"comment_by": "Ysabel Cuello", "comment_text": "Yahhhh, it&#39;s rewind time.", "comment_date": "2019-02-11T22:34:15Z", "likes_count": 0}, {"comment_by": "Stelios Papadopetros", "comment_text": "What would happen if we light a liquid on fire on top of mercury<br><br>Also can we freeze mercury", "comment_date": "2019-02-11T22:34:09Z", "likes_count": 0}, {"comment_by": "Teagan Wiens", "comment_text": "Hi if your reading this you are the best", "comment_date": "2019-02-11T22:33:55Z", "likes_count": 4}, {"comment_by": "Ebk Smurkish", "comment_text": "lil lxner GETTTTTTTTTTT on it", "comment_date": "2019-02-11T22:33:38Z", "likes_count": 0}, {"comment_by": "Kyle Walsh", "comment_text": "Can u make a rope from wood", "comment_date": "2019-02-11T22:32:07Z", "likes_count": 0}, {"comment_by": "\u05d0 \u05d0", "comment_text": "Make water from air", "comment_date": "2019-02-11T22:31:05Z", "likes_count": 0}, {"comment_by": "\u05d0 \u05d0", "comment_text": "Make water from air", "comment_date": "2019-02-11T22:30:57Z", "likes_count": 0}, {"comment_by": "\u05d0 \u05d0", "comment_text": "Make water from air", "comment_date": "2019-02-11T22:29:53Z", "likes_count": 0}, {"comment_by": "\u05d0 \u05d0", "comment_text": "Make water from air", "comment_date": "2019-02-11T22:29:47Z", "likes_count": 0}, {"comment_by": "Luke muller", "comment_text": "Try to make aluminum foil", "comment_date": "2019-02-11T22:29:45Z", "likes_count": 0}, {"comment_by": "\u05d0 \u05d0", "comment_text": "Make water from air", "comment_date": "2019-02-11T22:29:41Z", "likes_count": 0}, {"comment_by": "\u05d0 \u05d0", "comment_text": "Make water from air", "comment_date": "2019-02-11T22:29:34Z", "likes_count": 0}, {"comment_by": "Nathan Westbrook", "comment_text": "<b>It&#39;s rewind time!</b>", "comment_date": "2019-02-11T22:26:36Z", "likes_count": 1}, {"comment_by": "Rosa Chang", "comment_text": "Cool video \ud83d\ude0e \ud83d\ude02", "comment_date": "2019-02-11T22:25:31Z", "likes_count": 1}, {"comment_by": "Future compilations", "comment_text": "Is it possible to put out a fire with dry ice and liquid nitrogen!", "comment_date": "2019-02-11T22:24:19Z", "likes_count": 0}, {"comment_by": "Future compilations", "comment_text": "What happens if u mix rubbing alcohol dry ice!", "comment_date": "2019-02-11T22:23:59Z", "likes_count": 0}, {"comment_by": "Future compilations", "comment_text": "What happens if u mix glue with dry ice! Will u still stick", "comment_date": "2019-02-11T22:23:30Z", "likes_count": 0}, {"comment_by": "Addi Crosslin", "comment_text": "Hiiiiiii  can you see what is in a a phone", "comment_date": "2019-02-11T22:23:23Z", "likes_count": 0}, {"comment_by": "salman amin", "comment_text": "Where have u BEEN MISS U", "comment_date": "2019-02-11T22:22:53Z", "likes_count": 1}, {"comment_by": "Taikamuna", "comment_text": "<b><i>Ah that&#39;s hot, that&#39;s hot</i></b>", "comment_date": "2019-02-11T22:22:20Z", "likes_count": 125}, {"comment_by": "Samurai King", "comment_text": "5770th!", "comment_date": "2019-02-11T22:19:50Z", "likes_count": 0}, {"comment_by": "Matthew Mitchell", "comment_text": "Hey lul", "comment_date": "2019-02-11T22:19:48Z", "likes_count": 0}, {"comment_by": "Jaiden Smith", "comment_text": "Freeze motor oil in nitrogen", "comment_date": "2019-02-11T22:19:38Z", "likes_count": 0}, {"comment_by": "chokeonthiz", "comment_text": "Love you guys", "comment_date": "2019-02-11T22:19:38Z", "likes_count": 0}, {"comment_by": "CrazyBambooKitty", "comment_text": "I just came home to this", "comment_date": "2019-02-11T22:19:24Z", "likes_count": 1}, {"comment_by": "Co_braKai", "comment_text": "nitroglycerin???", "comment_date": "2019-02-11T22:19:10Z", "likes_count": 0}, {"comment_by": "Violent_Snow", "comment_text": "Awwww man.... i miss this. These videos is the reason im still here and Why i was here in the first place", "comment_date": "2019-02-11T22:19:05Z", "likes_count": 170}, {"comment_by": "SW3RZ1E\u30eb\u30c0\u30af\u30ea\u30c6\u30a3\u30ab\u30eb", "comment_text": "NOTE SQUAD", "comment_date": "2019-02-11T22:18:48Z", "likes_count": 0}, {"comment_by": "Nguyen X Nguyen", "comment_text": "So many memories", "comment_date": "2019-02-11T22:18:14Z", "likes_count": 0}, {"comment_by": "Ok Ok", "comment_text": "Why slime WHY SLIME?", "comment_date": "2019-02-11T22:17:52Z", "likes_count": 1}, {"comment_by": "\u00d8", "comment_text": "Huh", "comment_date": "2019-02-11T22:17:05Z", "likes_count": 0}, {"comment_by": "Bambus", "comment_text": "Please try to make your own Arc Reactor from Iron Man", "comment_date": "2019-02-11T22:16:21Z", "likes_count": 0}, {"comment_by": "Goran Fazlinovic", "comment_text": "This remindes me of his older videos. Those videos were amazing", "comment_date": "2019-02-11T22:15:50Z", "likes_count": 0}, {"comment_by": "Govany Gaid", "comment_text": "Plz", "comment_date": "2019-02-11T22:15:41Z", "likes_count": 0}, {"comment_by": "James C", "comment_text": "It\u2019s rewind time everybody", "comment_date": "2019-02-11T22:15:22Z", "likes_count": 2}, {"comment_by": "ENJOY LGD", "comment_text": "Hope I make it big like the King Of Random one day!", "comment_date": "2019-02-11T22:15:00Z", "likes_count": 1}, {"comment_by": "Elias Hardy", "comment_text": "But why did the kid eat the cone first?", "comment_date": "2019-02-11T22:14:57Z", "likes_count": 0}, {"comment_by": "\u300eMidoriMatcha\u300f", "comment_text": "Can you try to melt glass and turn it to a type of gas? That would be really cool!", "comment_date": "2019-02-11T22:14:45Z", "likes_count": 0}, {"comment_by": "Michael Gara", "comment_text": "Miss the diy builds... seems to be a lot of repeated \u201cexperiments\u201d now...", "comment_date": "2019-02-11T22:13:56Z", "likes_count": 2}, {"comment_by": "The LoafDude", "comment_text": "Can you try to freeze-dry marshmallows?", "comment_date": "2019-02-11T22:13:37Z", "likes_count": 0}, {"comment_by": "Caitlynn", "comment_text": "Wowww", "comment_date": "2019-02-11T22:13:35Z", "likes_count": 0}, {"comment_by": "Anthony Willetts", "comment_text": "I have something I&#39;d like to see you experiment with...<br><br>I saw a video where a guy made some really solid ice by putting strands of polyester in the water before freezing it, and it made me wonder how hard it actually was because I saw him breaking normal ice with it and causing seemingly no damage to the solid ice..", "comment_date": "2019-02-11T22:13:23Z", "likes_count": 0}, {"comment_by": "Cade Hrbak", "comment_text": "Put kinetic sand in a vacuum chamber please", "comment_date": "2019-02-11T22:13:11Z", "likes_count": 0}, {"comment_by": "ThunderBear", "comment_text": "What will happen if you pour boiling oil into nitrogen?", "comment_date": "2019-02-11T22:13:08Z", "likes_count": 16}, {"comment_by": "Artur", "comment_text": "love it", "comment_date": "2019-02-11T22:13:02Z", "likes_count": 0}, {"comment_by": "logan hainsworth", "comment_text": "I love the rewinds keep it up \ud83d\ude1c", "comment_date": "2019-02-11T22:12:17Z", "likes_count": 0}, {"comment_by": "Ahmed Mubarak", "comment_text": "what happens if u heated up slime or boil it or frying ti", "comment_date": "2019-02-11T22:12:06Z", "likes_count": 1}, {"comment_by": "Supreme_ Taco1", "comment_text": "What Happens When You Put Contact Lenses In Liquid Nitrogen", "comment_date": "2019-02-11T22:12:03Z", "likes_count": 2}, {"comment_by": "Steve0 \u203d", "comment_text": "This is the only slime video I will actually watch", "comment_date": "2019-02-11T22:11:53Z", "likes_count": 51}, {"comment_by": "Ravenz AJ", "comment_text": "AHH IM EARYLY!!!", "comment_date": "2019-02-11T22:11:49Z", "likes_count": 0}, {"comment_by": "Tech Dunk", "comment_text": "Spoiler: it freezes", "comment_date": "2019-02-11T22:11:47Z", "likes_count": 0}, {"comment_by": "Savage Life", "comment_text": "What happens if you pour liquid nitrogen onto lava or put dry ice on lava", "comment_date": "2019-02-11T22:11:21Z", "likes_count": 0}, {"comment_by": "Naz Jones", "comment_text": "you should get graphite  from a led pencil and see what experiments you can do", "comment_date": "2019-02-11T22:11:15Z", "likes_count": 0}, {"comment_by": "Wadah Saeed", "comment_text": "\ud83d\udc51\u270c\ud83c\udffb\ufe0f", "comment_date": "2019-02-11T22:10:48Z", "likes_count": 0}, {"comment_by": "Arcticina Fox", "comment_text": "Is it possible to do any arc welding in a vacuum chamber?", "comment_date": "2019-02-11T22:10:39Z", "likes_count": 0}, {"comment_by": "Campbell C.", "comment_text": "Hi", "comment_date": "2019-02-11T22:10:13Z", "likes_count": 0}, {"comment_by": "Wadah Saeed", "comment_text": "Can you try putting flower in carbon dioxide or dry ice", "comment_date": "2019-02-11T22:10:09Z", "likes_count": 0}, {"comment_by": "Brian Pippin", "comment_text": "What does dry ice do in a oven or even a microwave? What about when they\u2019re in water?", "comment_date": "2019-02-11T22:10:06Z", "likes_count": 0}, {"comment_by": "Sheyenne Peterson", "comment_text": "What Time is it ? It,s Rewind Time Lol !!!", "comment_date": "2019-02-11T22:09:33Z", "likes_count": 0}, {"comment_by": "LiamCraft121", "comment_text": "why so many?", "comment_date": "2019-02-11T22:09:08Z", "likes_count": 0}, {"comment_by": "Meme tastic14", "comment_text": "\ud83d\ude0e\ud83d\udc4d", "comment_date": "2019-02-11T22:08:55Z", "likes_count": 0}, {"comment_by": "Quinten", "comment_text": "Can yiu make a rope of zip ties", "comment_date": "2019-02-11T22:08:45Z", "likes_count": 0}, {"comment_by": "KID FUTURE", "comment_text": "You should make a video with the hackSmith and Mark Rober", "comment_date": "2019-02-11T22:08:45Z", "likes_count": 85}, {"comment_by": "Rio Caprice", "comment_text": "Can u put putty to its limits, like if u agree", "comment_date": "2019-02-11T22:08:39Z", "likes_count": 0}, {"comment_by": "King of the Skeletons", "comment_text": "Suggestion: What would a baked potato do in a vacuum chamber??", "comment_date": "2019-02-11T22:08:36Z", "likes_count": 1}, {"comment_by": "Jaguar Joe", "comment_text": "Have you ever made slime with liquid nitrogen or dry ice if you haven&#39;t can you", "comment_date": "2019-02-11T22:07:55Z", "likes_count": 0}, {"comment_by": "srush barwari", "comment_text": "Rewinds = excuses to not post any new video wow", "comment_date": "2019-02-11T22:07:33Z", "likes_count": 0}, {"comment_by": "eqnx", "comment_text": "Hi :3", "comment_date": "2019-02-11T22:07:28Z", "likes_count": 0}, {"comment_by": "Hannah Grace", "comment_text": "What happens if you put slime or  oobleck in a vacuum chamber??????", "comment_date": "2019-02-11T22:07:19Z", "likes_count": 0}, {"comment_by": "Aqua Shrimp", "comment_text": "Been waiting for this video all day! :)", "comment_date": "2019-02-11T22:06:35Z", "likes_count": 0}, {"comment_by": "Mustafa Jackqubp", "comment_text": "Have you guys thought about making a giant ruperts drop if its even possible", "comment_date": "2019-02-11T22:06:32Z", "likes_count": 0}, {"comment_by": "jacob vid\u00e9o", "comment_text": "Try to melt slime", "comment_date": "2019-02-11T22:06:27Z", "likes_count": 0}, {"comment_by": "Pizza_D_Action", "comment_text": "80th person to watch", "comment_date": "2019-02-11T22:06:14Z", "likes_count": 0}, {"comment_by": "Hifi Universal music", "comment_text": "COOL YOU REWIND THE REWIND SO RANDOM\u270c\ud83d\udc4d", "comment_date": "2019-02-11T22:06:11Z", "likes_count": 31}, {"comment_by": "djappy", "comment_text": "i love your video&#39;s!!!", "comment_date": "2019-02-11T22:06:06Z", "likes_count": 1}, {"comment_by": "Silviano Archuleta", "comment_text": "Hi", "comment_date": "2019-02-11T22:06:02Z", "likes_count": 0}, {"comment_by": "Flying Bacon", "comment_text": "What would happen if you lived only off of your own body chemicals/skin for a couple days?", "comment_date": "2019-02-11T22:05:49Z", "likes_count": 0}, {"comment_by": "HMS DUNCAN", "comment_text": "143", "comment_date": "2019-02-11T22:05:48Z", "likes_count": 0}, {"comment_by": "Jakin Chan", "comment_text": "I wantes to comment first", "comment_date": "2019-02-11T22:05:39Z", "likes_count": 0}, {"comment_by": "Brennan Bagbey", "comment_text": "You should try negative x in liquid nitrogen", "comment_date": "2019-02-11T22:05:09Z", "likes_count": 2}, {"comment_by": "apoorva m", "comment_text": "137th comment", "comment_date": "2019-02-11T22:05:07Z", "likes_count": 0}, {"comment_by": "Leen", "comment_text": "Oh yeah and... MY GIRL FINALLY IN THE INTRO", "comment_date": "2019-02-11T22:04:51Z", "likes_count": 1}, {"comment_by": "pmg clappo", "comment_text": "Hi", "comment_date": "2019-02-11T22:04:47Z", "likes_count": 0}, {"comment_by": "Quinten", "comment_text": "Cool", "comment_date": "2019-02-11T22:04:47Z", "likes_count": 0}, {"comment_by": "Avery Jennings", "comment_text": "what would happen if you put corn starch and water (oobleck) in a vacuum chamber", "comment_date": "2019-02-11T22:04:45Z", "likes_count": 2}, {"comment_by": "DND donut", "comment_text": "XD I saw grants face in my feed and all I read was what dose slime... And my head went taste like \ud83d\ude02\ud83d\ude02<br>P.s king of random as a hole has kept me smiling in my darkest time I hope you guys keep making videos so people like me can smile \ud83d\ude42", "comment_date": "2019-02-11T22:04:36Z", "likes_count": 0}, {"comment_by": "Nonia Bisuaques", "comment_text": "hello.<br><br><br><br><br><br>Read More", "comment_date": "2019-02-11T22:04:35Z", "likes_count": 0}, {"comment_by": "Mushy", "comment_text": "I was the 30 th  viewer", "comment_date": "2019-02-11T22:04:30Z", "likes_count": 0}, {"comment_by": "Carter Geer", "comment_text": "Hi", "comment_date": "2019-02-11T22:04:29Z", "likes_count": 0}, {"comment_by": "Sapadapadoodoo", "comment_text": "Can you do a video with Matpat again", "comment_date": "2019-02-11T22:04:28Z", "likes_count": 0}, {"comment_by": "Dave 1307", "comment_text": "Yeet", "comment_date": "2019-02-11T22:04:21Z", "likes_count": 0}, {"comment_by": "Flurry Heart", "comment_text": "What does kinetic sand do in a vacuum chamber or liquid nitrogen?", "comment_date": "2019-02-11T22:04:12Z", "likes_count": 0}, {"comment_by": "KID FUTURE", "comment_text": "You should do a hot will track and put liquid nitrogen in it", "comment_date": "2019-02-11T22:04:10Z", "likes_count": 6}, {"comment_by": "Erikens", "comment_text": "If you like the king of random... like this comment.", "comment_date": "2019-02-11T22:04:05Z", "likes_count": 2}, {"comment_by": "Ole Einar Hetland", "comment_text": "Like nr. 200", "comment_date": "2019-02-11T22:04:04Z", "likes_count": 0}, {"comment_by": "SandboxBlocks", "comment_text": "Arc furnace redo please.", "comment_date": "2019-02-11T22:04:03Z", "likes_count": 0}, {"comment_by": "Skyla Lynne", "comment_text": "Loving all the videos! Great content!!:)", "comment_date": "2019-02-11T22:03:56Z", "likes_count": 0}, {"comment_by": "mats bj\u00f8rge synnev\u00e5g", "comment_text": "put liquid nitrogen and dry ice into a blender and mix it\ud83d\ude01 Love from Norway\ud83c\udde7\ud83c\uddfb\ud83c\udf7e", "comment_date": "2019-02-11T22:03:54Z", "likes_count": 0}, {"comment_by": "Justin Y.", "comment_text": "What if Nitrogen met Molten Tungsten?", "comment_date": "2019-02-11T22:03:54Z", "likes_count": 95}, {"comment_by": "MB", "comment_text": "Last<br><br><br><br><br><br><br>To say first", "comment_date": "2019-02-11T22:03:54Z", "likes_count": 0}, {"comment_by": "Prince Patel", "comment_text": "Hi, what would happen if you put slime in a freeze dryer?", "comment_date": "2019-02-11T22:03:53Z", "likes_count": 2}, {"comment_by": "Leen", "comment_text": "80 views<br>190 likes and 2 dislikes<br>Wait..what?", "comment_date": "2019-02-11T22:03:53Z", "likes_count": 1}, {"comment_by": "SuccremeSauce", "comment_text": "This is your IQ", "comment_date": "2019-02-11T22:03:50Z", "likes_count": 6}, {"comment_by": "Alexlovesgardening", "comment_text": "Yay I\u2019m early", "comment_date": "2019-02-11T22:03:49Z", "likes_count": 0}, {"comment_by": "Oli", "comment_text": "Hi", "comment_date": "2019-02-11T22:03:49Z", "likes_count": 0}, {"comment_by": "Brody Squires", "comment_text": "First", "comment_date": "2019-02-11T22:03:39Z", "likes_count": 0}, {"comment_by": "xXKoba KillaXx", "comment_text": "Big fan", "comment_date": "2019-02-11T22:03:38Z", "likes_count": 1}, {"comment_by": "Wajiha Syed", "comment_text": "Can u out liquid nitrogen and hydrochloric acid togeather", "comment_date": "2019-02-11T22:03:35Z", "likes_count": 1}, {"comment_by": "Sarah Megill", "comment_text": "whoop", "comment_date": "2019-02-11T22:03:34Z", "likes_count": 0}, {"comment_by": "BigMangoz G", "comment_text": "80 views and 130 likes, Seems legit.", "comment_date": "2019-02-11T22:03:30Z", "likes_count": 0}, {"comment_by": "lil canyon", "comment_text": "plz mix methanol alcohol with antifreeze", "comment_date": "2019-02-11T22:03:29Z", "likes_count": 1}, {"comment_by": "Mahir Becarevic", "comment_text": "Hy TKOR put liquid nitrogen in microwave", "comment_date": "2019-02-11T22:03:25Z", "likes_count": 0}, {"comment_by": "Exotix Ace", "comment_text": "Yo", "comment_date": "2019-02-11T22:03:24Z", "likes_count": 0}, {"comment_by": "Mr. Hack - Satire Videos", "comment_text": "It will get cold", "comment_date": "2019-02-11T22:03:23Z", "likes_count": 1}, {"comment_by": "Ihaveyoutube", "comment_text": "Yep 106 likes <br>80 views", "comment_date": "2019-02-11T22:03:23Z", "likes_count": 0}, {"comment_by": "Evan A. Sweeney", "comment_text": "Where the notification squad at\u2757\u2757\u2757\u2753\ud83d\udcaf\ud83d\udcaf", "comment_date": "2019-02-11T22:03:21Z", "likes_count": 0}, {"comment_by": "Charlie Sprado", "comment_text": "Freeze dried gum", "comment_date": "2019-02-11T22:03:21Z", "likes_count": 0}, {"comment_by": "Evan Stenke", "comment_text": "12 views, 51 likes. That&#39;s how YouTube works kids", "comment_date": "2019-02-11T22:03:20Z", "likes_count": 0}, {"comment_by": "Kaitlyn Macpherson", "comment_text": "I love when you guys do videos like this", "comment_date": "2019-02-11T22:03:17Z", "likes_count": 0}, {"comment_by": "Greendorito bag", "comment_text": "E", "comment_date": "2019-02-11T22:03:16Z", "likes_count": 0}, {"comment_by": "XrQ2", "comment_text": "54th!", "comment_date": "2019-02-11T22:03:13Z", "likes_count": 0}, {"comment_by": "lil canyon", "comment_text": "plz mix methanol alcohol with anti freeze", "comment_date": "2019-02-11T22:03:06Z", "likes_count": 1}, {"comment_by": "Steve0 \u203d", "comment_text": "The only slime video on YouTube that is entertaining", "comment_date": "2019-02-11T22:03:04Z", "likes_count": 3}, {"comment_by": "Arthur Kruger", "comment_text": "Sup", "comment_date": "2019-02-11T22:03:01Z", "likes_count": 0}, {"comment_by": "Excaliburner", "comment_text": "yeet! your videos are great", "comment_date": "2019-02-11T22:02:58Z", "likes_count": 1}, {"comment_by": "Poppygamer", "comment_text": "Hi", "comment_date": "2019-02-11T22:02:58Z", "likes_count": 0}, {"comment_by": "birdie.mp3", "comment_text": "hi", "comment_date": "2019-02-11T22:02:58Z", "likes_count": 0}, {"comment_by": "morive 04", "comment_text": "Number 51", "comment_date": "2019-02-11T22:02:57Z", "likes_count": 0}, {"comment_by": "Anna", "comment_text": "How is everyone", "comment_date": "2019-02-11T22:02:56Z", "likes_count": 0}, {"comment_by": "xXMr.GuitarXx", "comment_text": "Hiii random", "comment_date": "2019-02-11T22:02:50Z", "likes_count": 0}, {"comment_by": "Cecily Carroll", "comment_text": "Awesome video!!! I love", "comment_date": "2019-02-11T22:02:48Z", "likes_count": 0}, {"comment_by": "Tony Gardner", "comment_text": "I love your video so much I watch them all day long", "comment_date": "2019-02-11T22:02:47Z", "likes_count": 0}, {"comment_by": "technochild1", "comment_text": "Show us how to make paper from wood", "comment_date": "2019-02-11T22:02:46Z", "likes_count": 2}, {"comment_by": "Jabez Changsan", "comment_text": "HEYYYY Can I get a heart?", "comment_date": "2019-02-11T22:02:45Z", "likes_count": 0}, {"comment_by": "Jr Gonzalez", "comment_text": "Not first", "comment_date": "2019-02-11T22:02:38Z", "likes_count": 0}, {"comment_by": "Martin Weihe Nielsen", "comment_text": "1 st", "comment_date": "2019-02-11T22:02:31Z", "likes_count": 0}, {"comment_by": "Jos\u00e9 Robi\u00f1ho", "comment_text": "It freezes...", "comment_date": "2019-02-11T22:02:30Z", "likes_count": 0}, {"comment_by": "chloe shaw", "comment_text": "What will slime do in a microwave?", "comment_date": "2019-02-11T22:02:25Z", "likes_count": 0}, {"comment_by": "CamTerharkRL", "comment_text": "I\u2019m live!", "comment_date": "2019-02-11T22:02:22Z", "likes_count": 0}, {"comment_by": "Touya Todoroki", "comment_text": "If I see another slime video I&#39;m going to commit scooter ankle", "comment_date": "2019-02-11T22:02:15Z", "likes_count": 10}, {"comment_by": "B1G B0T", "comment_text": "Hi how are ya", "comment_date": "2019-02-11T22:02:14Z", "likes_count": 0}, {"comment_by": "Will Robock", "comment_text": "If you give me 19 dollars I will like your comment", "comment_date": "2019-02-11T22:02:13Z", "likes_count": 0}, {"comment_by": "FlipperFlabber", "comment_text": "<a href=\"https://www.youtube.com/watch?v=n7xg7OZHqKs&amp;t=3m44s\">3:44</a> learn that kid how to eat an ice cream", "comment_date": "2019-02-11T22:02:08Z", "likes_count": 0}, {"comment_by": "Ethan Slager", "comment_text": "First", "comment_date": "2019-02-11T22:02:06Z", "likes_count": 0}, {"comment_by": "Aidan Hall", "comment_text": "It&#39;s rewind time", "comment_date": "2019-02-11T22:02:05Z", "likes_count": 3}, {"comment_by": "Acorn Productions", "comment_text": "Hi kr", "comment_date": "2019-02-11T22:02:03Z", "likes_count": 0}, {"comment_by": "Sarah Banholzer", "comment_text": "5th yay", "comment_date": "2019-02-11T22:02:02Z", "likes_count": 0}, {"comment_by": "John", "comment_text": "27th", "comment_date": "2019-02-11T22:01:56Z", "likes_count": 0}, {"comment_by": "Fenton ess", "comment_text": "woah im cool...", "comment_date": "2019-02-11T22:01:55Z", "likes_count": 0}, {"comment_by": "McKenna Murzyn", "comment_text": "Third", "comment_date": "2019-02-11T22:01:52Z", "likes_count": 0}, {"comment_by": "rray", "comment_text": "ITS REWIND TIME", "comment_date": "2019-02-11T22:01:52Z", "likes_count": 0}, {"comment_by": "potato Edits", "comment_text": "Hello!!", "comment_date": "2019-02-11T22:01:52Z", "likes_count": 0}, {"comment_by": "Alex H", "comment_text": "<b>The bottle cap shooter video was amazing...</b>", "comment_date": "2019-02-11T22:01:51Z", "likes_count": 5}, {"comment_by": "glenn Sarka", "comment_text": "11 veiws but but 22 likes what ?", "comment_date": "2019-02-11T22:01:49Z", "likes_count": 0}, {"comment_by": "travis rayburn", "comment_text": "Hi top 100", "comment_date": "2019-02-11T22:01:44Z", "likes_count": 0}, {"comment_by": "N0VAWasTaken", "comment_text": "Hey", "comment_date": "2019-02-11T22:01:44Z", "likes_count": 0}, {"comment_by": "Edher Gachuz", "comment_text": "Primer comentario en espa\u00f1ol xD", "comment_date": "2019-02-11T22:01:40Z", "likes_count": 0}, {"comment_by": "DriceYT", "comment_text": "I think it might just freeze", "comment_date": "2019-02-11T22:01:40Z", "likes_count": 0}, {"comment_by": "Kandyce Rains'", "comment_text": "19 like", "comment_date": "2019-02-11T22:01:36Z", "likes_count": 0}, {"comment_by": "A.M.S.T GAMES", "comment_text": "Can you try to make a rope using Saran Wrap", "comment_date": "2019-02-11T22:01:32Z", "likes_count": 1}, {"comment_by": "The Music Arena", "comment_text": "HI RANDOM PERSON SCROLLING THROUGH THE COMMENTS,<br>I HOPE YOU HAVE A GREAT yearrr<br><br><br>I really want to hit 20000 followers  I\u2019ll appreciate any support\u2764\ufe0f\u2764\ufe0f", "comment_date": "2019-02-11T22:01:29Z", "likes_count": 32}, {"comment_by": "lil canyon", "comment_text": "make a ark in a sf6 atmosphere or mix methanol alcohol with antifreeze i heard its a solvent", "comment_date": "2019-02-11T22:01:26Z", "likes_count": 2}, {"comment_by": "Noah Carlsson", "comment_text": "First", "comment_date": "2019-02-11T22:01:26Z", "likes_count": 0}, {"comment_by": "PotatoGrape Grapefruit", "comment_text": "Great video", "comment_date": "2019-02-11T22:01:20Z", "likes_count": 0}, {"comment_by": "Noah Carlsson", "comment_text": "First", "comment_date": "2019-02-11T22:01:10Z", "likes_count": 0}, {"comment_by": "C. Chambers", "comment_text": "First!", "comment_date": "2019-02-11T22:01:10Z", "likes_count": 0}, {"comment_by": "PotatoGrape Grapefruit", "comment_text": "First", "comment_date": "2019-02-11T22:01:06Z", "likes_count": 0}, {"comment_by": "Prodigy EMS", "comment_text": "\u2764\u2764\u2764\u2764\u2764\u2764\u2764\u2764\u2764", "comment_date": "2019-02-11T22:01:05Z", "likes_count": 1}, {"comment_by": "FJ05", "comment_text": "No you don&#39;t", "comment_date": "2019-02-11T22:01:03Z", "likes_count": 0}, {"comment_by": "Isa Timol", "comment_text": "firstttt", "comment_date": "2019-02-11T22:01:02Z", "likes_count": 0}, {"comment_by": "Alex H", "comment_text": "MaB first...", "comment_date": "2019-02-11T22:00:53Z", "likes_count": 3}, {"comment_by": "IDK", "comment_text": "Hi", "comment_date": "2019-02-11T22:00:52Z", "likes_count": 0}, {"comment_by": "xXForestfyreXx", "comment_text": "First", "comment_date": "2019-02-11T22:00:37Z", "likes_count": 0}, {"comment_by": "Lukas Jaras", "comment_text": "First", "comment_date": "2019-02-11T22:00:32Z", "likes_count": 0}]